{"ok":true,"source":"cityrail-osm-snapshot","endpoint":"openstreetmap-api","bbox":[34.05,108.65,34.45,109.25],"routes":[{"relationId":5454552,"key":"西安地铁|1","name":"西安地铁1号线：咸阳西站 → 纺织城","ref":"1","network":"西安地铁","route":"subway","color":"#0077c8","isLoop":false,"loopMode":"","loopReason":"","loopTerminalDistanceM":37837,"stations":[{"name":"咸阳西站","lat":34.3352826,"lng":108.6580098,"rawLat":34.3352826,"rawLng":108.6580098,"transferKey":"咸阳西","platformKey":"5454552:0:咸阳西","osmRefs":["node/11207125791"]},{"name":"宝泉路","lat":34.3267505,"lng":108.6609766,"rawLat":34.3267505,"rawLng":108.6609766,"transferKey":"宝泉路","platformKey":"5454552:1:宝泉路","osmRefs":["node/11207125787"]},{"name":"中华西路","lat":34.3146934,"lng":108.6691153,"rawLat":34.3146934,"rawLng":108.6691153,"transferKey":"中华西路","platformKey":"5454552:2:中华西路","osmRefs":["node/11207125783"]},{"name":"安谷","lat":34.3076045,"lng":108.6890356,"rawLat":34.3076045,"rawLng":108.6890356,"transferKey":"安谷","platformKey":"5454552:3:安谷","osmRefs":["node/11207125781"]},{"name":"陈杨寨","lat":34.3151288,"lng":108.7022446,"rawLat":34.3151288,"rawLng":108.7022446,"transferKey":"陈杨寨","platformKey":"5454552:4:陈杨寨","osmRefs":["node/11207125777"]},{"name":"白马河","lat":34.3180837,"lng":108.7225234,"rawLat":34.3180837,"rawLng":108.7225234,"transferKey":"白马河","platformKey":"5454552:5:白马河","osmRefs":["node/11207125774"]},{"name":"陕西中医药大学","lat":34.3196831,"lng":108.7334807,"rawLat":34.3196831,"rawLng":108.7334807,"transferKey":"陕西中医药大学","platformKey":"5454552:6:陕西中医药大学","osmRefs":["node/11207125771"]},{"name":"沣河森林公园","lat":34.3217082,"lng":108.7482241,"rawLat":34.3217082,"rawLng":108.7482241,"transferKey":"沣河森林公园","platformKey":"5454552:7:沣河森林公园","osmRefs":["node/9560059864"]},{"name":"北槐","lat":34.3187129,"lng":108.7583663,"rawLat":34.3187129,"rawLng":108.7583663,"transferKey":"北槐","platformKey":"5454552:8:北槐","osmRefs":["node/9560059886"]},{"name":"上林路","lat":34.3146474,"lng":108.7727844,"rawLat":34.3146474,"rawLng":108.7727844,"transferKey":"上林路","platformKey":"5454552:9:上林路","osmRefs":["node/9560059897"]},{"name":"沣东自贸园","lat":34.3083982,"lng":108.7924968,"rawLat":34.3083982,"rawLng":108.7924968,"transferKey":"沣东自贸园","platformKey":"5454552:10:沣东自贸园","osmRefs":["node/9591708559"]},{"name":"后卫寨","lat":34.30148,"lng":108.8089124,"rawLat":34.30148,"rawLng":108.8089124,"transferKey":"后卫寨","platformKey":"5454552:11:后卫寨","osmRefs":["node/9591708572"]},{"name":"三桥","lat":34.2915751,"lng":108.827151,"rawLat":34.2915751,"rawLng":108.827151,"transferKey":"三桥","platformKey":"5454552:12:三桥","osmRefs":["node/9591666348"]},{"name":"皂河","lat":34.2858578,"lng":108.8476552,"rawLat":34.2858745,"rawLng":108.8476975,"transferKey":"皂河","platformKey":"5454552:13:皂河","osmRefs":["node/9591666365"]},{"name":"枣园","lat":34.2806238,"lng":108.8579553,"rawLat":34.2806238,"rawLng":108.8579553,"transferKey":"枣园","platformKey":"5454552:14:枣园","osmRefs":["node/9591666385"]},{"name":"汉城路","lat":34.2745385,"lng":108.8690924,"rawLat":34.2745385,"rawLng":108.8690924,"transferKey":"汉城路","platformKey":"5454552:15:汉城路","osmRefs":["node/9591666390"]},{"name":"开远门","lat":34.2708794,"lng":108.8878983,"rawLat":34.2708794,"rawLng":108.8878983,"transferKey":"开远门","platformKey":"5454552:16:开远门","osmRefs":["node/9591706906"]},{"name":"劳动路","lat":34.2710006,"lng":108.9052436,"rawLat":34.2710006,"rawLng":108.9052436,"transferKey":"劳动路","platformKey":"5454552:17:劳动路","osmRefs":["node/9591706912"]},{"name":"玉祥门","lat":34.271044,"lng":108.9162951,"rawLat":34.271044,"rawLng":108.9162951,"transferKey":"玉祥门","platformKey":"5454552:18:玉祥门","osmRefs":["node/9591706913"]},{"name":"洒金桥","lat":34.2711933,"lng":108.9293752,"rawLat":34.2711933,"rawLng":108.9293752,"transferKey":"洒金桥","platformKey":"5454552:19:洒金桥","osmRefs":["node/9591769828"]},{"name":"北大街","lat":34.2715084,"lng":108.9425131,"rawLat":34.2715084,"rawLng":108.9425131,"transferKey":"北大街","platformKey":"5454552:20:北大街","osmRefs":["node/9591752568"]},{"name":"五路口","lat":34.2714801,"lng":108.9582248,"rawLat":34.2714801,"rawLng":108.9582248,"transferKey":"五路口","platformKey":"5454552:21:五路口","osmRefs":["node/9591752579"]},{"name":"朝阳门","lat":34.2714109,"lng":108.9693858,"rawLat":34.2714109,"rawLng":108.9693858,"transferKey":"朝阳门","platformKey":"5454552:22:朝阳门","osmRefs":["node/9591752594"]},{"name":"康复路","lat":34.2709177,"lng":108.9795901,"rawLat":34.2709177,"rawLng":108.9795901,"transferKey":"康复路","platformKey":"5454552:23:康复路","osmRefs":["node/9591821079"]},{"name":"通化门","lat":34.2709228,"lng":108.9899154,"rawLat":34.2709228,"rawLng":108.9899154,"transferKey":"通化门","platformKey":"5454552:24:通化门","osmRefs":["node/9591821088"]},{"name":"万寿路","lat":34.2708337,"lng":109.0081503,"rawLat":34.2708337,"rawLng":109.0081503,"transferKey":"万寿路","platformKey":"5454552:25:万寿路","osmRefs":["node/9591902319"]},{"name":"长乐坡","lat":34.273287,"lng":109.0257845,"rawLat":34.273287,"rawLng":109.0257845,"transferKey":"长乐坡","platformKey":"5454552:26:长乐坡","osmRefs":["node/9591902329"]},{"name":"浐河","lat":34.2750323,"lng":109.0393613,"rawLat":34.2750323,"rawLng":109.0393613,"transferKey":"浐河","platformKey":"5454552:27:浐河","osmRefs":["node/9591902345"]},{"name":"半坡","lat":34.2764275,"lng":109.0511053,"rawLat":34.2764275,"rawLng":109.0511053,"transferKey":"半坡","platformKey":"5454552:28:半坡","osmRefs":["node/9591736807"]},{"name":"纺织城","lat":34.2807715,"lng":109.0646395,"rawLat":34.2807715,"rawLng":109.0646395,"transferKey":"纺织城","platformKey":"5454552:29:纺织城","osmRefs":["node/9591736813"]}],"waypoints":[{"lat":34.3281347,"lng":108.6604671,"segIdx":0,"order":0},{"lat":34.3230121,"lng":108.6622578,"segIdx":1,"order":0},{"lat":34.3185753,"lng":108.6637649,"segIdx":1,"order":1},{"lat":34.3169116,"lng":108.6657839,"segIdx":1,"order":2},{"lat":34.3135466,"lng":108.6707903,"segIdx":2,"order":0},{"lat":34.3041814,"lng":108.6845336,"segIdx":2,"order":1},{"lat":34.3042828,"lng":108.685659,"segIdx":2,"order":2},{"lat":34.3123155,"lng":108.6938906,"segIdx":3,"order":0},{"lat":34.3142069,"lng":108.69644,"segIdx":3,"order":1},{"lat":34.3160095,"lng":108.708243,"segIdx":4,"order":0},{"lat":34.3175068,"lng":108.7186342,"segIdx":4,"order":1},{"lat":34.3189147,"lng":108.7281438,"segIdx":5,"order":0},{"lat":34.3201686,"lng":108.7368533,"segIdx":6,"order":0},{"lat":34.3216898,"lng":108.7469962,"segIdx":6,"order":1},{"lat":34.3217125,"lng":108.7491312,"segIdx":7,"order":0},{"lat":34.3199302,"lng":108.75584,"segIdx":7,"order":1},{"lat":34.3184458,"lng":108.758936,"segIdx":8,"order":0},{"lat":34.3155992,"lng":108.7697552,"segIdx":8,"order":1},{"lat":34.3141375,"lng":108.7742019,"segIdx":9,"order":0},{"lat":34.3094129,"lng":108.788553,"segIdx":9,"order":1},{"lat":34.3079849,"lng":108.7940515,"segIdx":10,"order":0},{"lat":34.3018108,"lng":108.8082307,"segIdx":10,"order":1},{"lat":34.3011353,"lng":108.8096184,"segIdx":11,"order":0},{"lat":34.2950485,"lng":108.8217518,"segIdx":11,"order":1},{"lat":34.2911415,"lng":108.8278889,"segIdx":12,"order":0},{"lat":34.2890714,"lng":108.84013,"segIdx":12,"order":1},{"lat":34.2862507,"lng":108.847049,"segIdx":12,"order":2},{"lat":34.2849841,"lng":108.8492428,"segIdx":13,"order":0},{"lat":34.2809921,"lng":108.8572712,"segIdx":13,"order":1},{"lat":34.280171,"lng":108.8587962,"segIdx":14,"order":0},{"lat":34.2749429,"lng":108.8684109,"segIdx":14,"order":1},{"lat":34.2741802,"lng":108.8697169,"segIdx":15,"order":0},{"lat":34.2708229,"lng":108.8764477,"segIdx":15,"order":1},{"lat":34.2708746,"lng":108.886705,"segIdx":15,"order":2},{"lat":34.2709113,"lng":108.8958113,"segIdx":16,"order":0},{"lat":34.2710052,"lng":108.8999252,"segIdx":16,"order":1},{"lat":34.2710083,"lng":108.9072004,"segIdx":17,"order":0},{"lat":34.2710508,"lng":108.9171707,"segIdx":18,"order":0},{"lat":34.2711259,"lng":108.9210947,"segIdx":18,"order":1},{"lat":34.2712012,"lng":108.9300153,"segIdx":19,"order":0},{"lat":34.2714941,"lng":108.9412678,"segIdx":19,"order":1},{"lat":34.2714891,"lng":108.9448738,"segIdx":20,"order":0},{"lat":34.2715007,"lng":108.9560006,"segIdx":20,"order":1},{"lat":34.2714724,"lng":108.9631588,"segIdx":21,"order":0},{"lat":34.2715026,"lng":108.9679914,"segIdx":21,"order":1},{"lat":34.2711853,"lng":108.9721391,"segIdx":22,"order":0},{"lat":34.2709204,"lng":108.9783403,"segIdx":22,"order":1},{"lat":34.2709243,"lng":108.9810142,"segIdx":23,"order":0},{"lat":34.2709268,"lng":108.9914382,"segIdx":24,"order":0},{"lat":34.2708636,"lng":108.9981649,"segIdx":24,"order":1},{"lat":34.2708168,"lng":109.0114627,"segIdx":25,"order":0},{"lat":34.2728913,"lng":109.0205579,"segIdx":25,"order":1},{"lat":34.2732274,"lng":109.0249975,"segIdx":25,"order":2},{"lat":34.2733535,"lng":109.0265497,"segIdx":26,"order":0},{"lat":34.2747845,"lng":109.0385073,"segIdx":26,"order":1},{"lat":34.2753784,"lng":109.0405542,"segIdx":27,"order":0},{"lat":34.276148,"lng":109.0436925,"segIdx":27,"order":1},{"lat":34.2763065,"lng":109.0504396,"segIdx":27,"order":2},{"lat":34.2765555,"lng":109.0518178,"segIdx":28,"order":0},{"lat":34.2802621,"lng":109.0581167,"segIdx":28,"order":1},{"lat":34.2807743,"lng":109.0638971,"segIdx":28,"order":2}]},{"relationId":5454553,"key":"西安地铁|2","name":"西安地铁2号线：草滩 → 常宁宫","ref":"2","network":"西安地铁","route":"subway","color":"#ef3340","isLoop":false,"loopMode":"","loopReason":"","loopTerminalDistanceM":31978,"stations":[{"name":"草滩","lat":34.400362,"lng":108.9550465,"rawLat":34.400362,"rawLng":108.9550465,"transferKey":"草滩","platformKey":"5454553:0:草滩","osmRefs":["node/11018994734"]},{"name":"红会医院北区","lat":34.3950682,"lng":108.9408229,"rawLat":34.3950682,"rawLng":108.9408229,"transferKey":"红会医院北区","platformKey":"5454553:1:红会医院北区","osmRefs":["node/11018994727"]},{"name":"西安北站","lat":34.3775527,"lng":108.9339028,"rawLat":34.3775527,"rawLng":108.9339028,"transferKey":"西安北","platformKey":"5454553:2:西安北","osmRefs":["node/9553275492"]},{"name":"北苑","lat":34.3635155,"lng":108.9405045,"rawLat":34.3635155,"rawLng":108.9405045,"transferKey":"北苑","platformKey":"5454553:3:北苑","osmRefs":["node/9553275495"]},{"name":"凤城十路","lat":34.3539878,"lng":108.9429374,"rawLat":34.3539878,"rawLng":108.9429374,"transferKey":"凤城十路","platformKey":"5454553:4:凤城十路","osmRefs":["node/9553275516"]},{"name":"行政中心","lat":34.342583,"lng":108.9424982,"rawLat":34.342583,"rawLng":108.9424982,"transferKey":"行政中心","platformKey":"5454553:5:行政中心","osmRefs":["node/9553275508"]},{"name":"凤城五路","lat":34.3313731,"lng":108.9425016,"rawLat":34.3313731,"rawLng":108.9425016,"transferKey":"凤城五路","platformKey":"5454553:6:凤城五路","osmRefs":["node/9553308089"]},{"name":"青少年中心","lat":34.3194188,"lng":108.9424927,"rawLat":34.3194188,"rawLng":108.9424927,"transferKey":"青少年中心","platformKey":"5454553:7:青少年中心","osmRefs":["node/9553308100"]},{"name":"大明宫西","lat":34.3065315,"lng":108.9425084,"rawLat":34.3065315,"rawLng":108.9425084,"transferKey":"大明宫西","platformKey":"5454553:8:大明宫西","osmRefs":["node/12120796766"]},{"name":"龙首原","lat":34.2934973,"lng":108.9424739,"rawLat":34.2934973,"rawLng":108.9424739,"transferKey":"龙首原","platformKey":"5454553:9:龙首原","osmRefs":["node/9553764105"]},{"name":"安远门","lat":34.2828847,"lng":108.9424487,"rawLat":34.2828847,"rawLng":108.9424487,"transferKey":"安远门","platformKey":"5454553:10:安远门","osmRefs":["node/9553764111"]},{"name":"北大街","lat":34.2715305,"lng":108.9424458,"rawLat":34.2715305,"rawLng":108.9424458,"transferKey":"北大街","platformKey":"5454553:11:北大街","osmRefs":["node/9553815918"]},{"name":"钟楼","lat":34.2629505,"lng":108.9422254,"rawLat":34.2629505,"rawLng":108.9422254,"transferKey":"钟楼","platformKey":"5454553:12:钟楼","osmRefs":["node/9553997113"]},{"name":"永宁门","lat":34.2499127,"lng":108.9421951,"rawLat":34.2499127,"rawLng":108.9421951,"transferKey":"永宁门","platformKey":"5454553:13:永宁门","osmRefs":["node/9554027422"]},{"name":"南稍门","lat":34.2419883,"lng":108.9421493,"rawLat":34.2419883,"rawLng":108.9421493,"transferKey":"南稍门","platformKey":"5454553:14:南稍门","osmRefs":["node/9554027431"]},{"name":"体育场","lat":34.2341002,"lng":108.9420753,"rawLat":34.2341002,"rawLng":108.9420753,"transferKey":"体育场","platformKey":"5454553:15:体育场","osmRefs":["node/9554022003"]},{"name":"小寨","lat":34.2243986,"lng":108.9419656,"rawLat":34.2243986,"rawLng":108.9419656,"transferKey":"小寨","platformKey":"5454553:16:小寨","osmRefs":["node/9554045518"]},{"name":"八里村","lat":34.214176,"lng":108.9419075,"rawLat":34.214176,"rawLng":108.9419075,"transferKey":"八里村","platformKey":"5454553:17:八里村","osmRefs":["node/9554045474"]},{"name":"电视塔","lat":34.1996152,"lng":108.9426563,"rawLat":34.1996152,"rawLng":108.9426563,"transferKey":"电视塔","platformKey":"5454553:18:电视塔","osmRefs":["node/9554045487"]},{"name":"三爻","lat":34.1845203,"lng":108.9411423,"rawLat":34.1845203,"rawLng":108.9411423,"transferKey":"三爻","platformKey":"5454553:19:三爻","osmRefs":["node/9555593501"]},{"name":"凤栖原","lat":34.1707935,"lng":108.9404639,"rawLat":34.1707935,"rawLng":108.9404639,"transferKey":"凤栖原","platformKey":"5454553:20:凤栖原","osmRefs":["node/9555593514"]},{"name":"航天城","lat":34.1596487,"lng":108.9398861,"rawLat":34.1596487,"rawLng":108.9398861,"transferKey":"航天城","platformKey":"5454553:21:航天城","osmRefs":["node/9555607523"]},{"name":"韦曲南","lat":34.1437361,"lng":108.9407895,"rawLat":34.1437361,"rawLng":108.9407895,"transferKey":"韦曲南","platformKey":"5454553:22:韦曲南","osmRefs":["node/9555607540"]},{"name":"何家营","lat":34.1288795,"lng":108.9352384,"rawLat":34.1288795,"rawLng":108.9352384,"transferKey":"何家营","platformKey":"5454553:23:何家营","osmRefs":["node/11019603140"]},{"name":"常宁宫","lat":34.1133068,"lng":108.933927,"rawLat":34.1133068,"rawLng":108.933927,"transferKey":"常宁宫","platformKey":"5454553:24:常宁宫","osmRefs":["node/11019603156"]}],"waypoints":[{"lat":34.3996682,"lng":108.953521,"segIdx":0,"order":0},{"lat":34.3961036,"lng":108.9438842,"segIdx":0,"order":1},{"lat":34.3946794,"lng":108.939636,"segIdx":1,"order":0},{"lat":34.3935081,"lng":108.936819,"segIdx":1,"order":1},{"lat":34.3924248,"lng":108.9359067,"segIdx":1,"order":2},{"lat":34.3905262,"lng":108.9352252,"segIdx":1,"order":3},{"lat":34.3872325,"lng":108.9357343,"segIdx":1,"order":4},{"lat":34.3829178,"lng":108.9324102,"segIdx":1,"order":5},{"lat":34.379404,"lng":108.9332058,"segIdx":1,"order":6},{"lat":34.3761417,"lng":108.9344076,"segIdx":2,"order":0},{"lat":34.3646557,"lng":108.9400242,"segIdx":2,"order":1},{"lat":34.3628964,"lng":108.9408202,"segIdx":3,"order":0},{"lat":34.3581089,"lng":108.9434814,"segIdx":3,"order":1},{"lat":34.3566642,"lng":108.9436047,"segIdx":3,"order":2},{"lat":34.353417,"lng":108.9428421,"segIdx":4,"order":0},{"lat":34.3508116,"lng":108.9425542,"segIdx":4,"order":1},{"lat":34.3406849,"lng":108.9425194,"segIdx":5,"order":0},{"lat":34.3350068,"lng":108.9425101,"segIdx":5,"order":1},{"lat":34.3281299,"lng":108.9425123,"segIdx":6,"order":0},{"lat":34.3207567,"lng":108.9424948,"segIdx":6,"order":1},{"lat":34.3133537,"lng":108.9425265,"segIdx":7,"order":0},{"lat":34.2880258,"lng":108.9424709,"segIdx":9,"order":0},{"lat":34.2815016,"lng":108.942472,"segIdx":10,"order":0},{"lat":34.2683875,"lng":108.9424168,"segIdx":11,"order":0},{"lat":34.2646045,"lng":108.9423536,"segIdx":11,"order":1},{"lat":34.2619288,"lng":108.9421875,"segIdx":12,"order":0},{"lat":34.2505472,"lng":108.9422129,"segIdx":12,"order":1},{"lat":34.2489266,"lng":108.9422078,"segIdx":13,"order":0},{"lat":34.2436274,"lng":108.9421505,"segIdx":13,"order":1},{"lat":34.2414804,"lng":108.9421278,"segIdx":14,"order":0},{"lat":34.2354962,"lng":108.9420938,"segIdx":14,"order":1},{"lat":34.2331584,"lng":108.942075,"segIdx":15,"order":0},{"lat":34.2271744,"lng":108.9419615,"segIdx":15,"order":1},{"lat":34.2233576,"lng":108.9419746,"segIdx":16,"order":0},{"lat":34.2201706,"lng":108.9419601,"segIdx":16,"order":1},{"lat":34.2131581,"lng":108.9418996,"segIdx":17,"order":0},{"lat":34.2021757,"lng":108.9418749,"segIdx":17,"order":1},{"lat":34.1990551,"lng":108.9428291,"segIdx":18,"order":0},{"lat":34.1976096,"lng":108.9431946,"segIdx":18,"order":1},{"lat":34.1872244,"lng":108.9407828,"segIdx":18,"order":2},{"lat":34.1825944,"lng":108.9414662,"segIdx":19,"order":0},{"lat":34.1761415,"lng":108.9403261,"segIdx":19,"order":1},{"lat":34.169709,"lng":108.9404733,"segIdx":20,"order":0},{"lat":34.1637442,"lng":108.9404944,"segIdx":20,"order":1},{"lat":34.1589273,"lng":108.9397697,"segIdx":21,"order":0},{"lat":34.1547352,"lng":108.9408853,"segIdx":21,"order":1},{"lat":34.1446735,"lng":108.9408165,"segIdx":21,"order":2},{"lat":34.1430167,"lng":108.9407077,"segIdx":22,"order":0},{"lat":34.1321869,"lng":108.9363011,"segIdx":22,"order":1},{"lat":34.1281754,"lng":108.9350121,"segIdx":23,"order":0},{"lat":34.1143748,"lng":108.9339688,"segIdx":23,"order":1}]},{"relationId":7719093,"key":"西安地铁|3","name":"西安地铁3号线：鱼化寨→保税区","ref":"3","network":"西安地铁","route":"subway","color":"#b688a9","isLoop":false,"loopMode":"","loopReason":"","loopTerminalDistanceM":9833,"stations":[{"name":"保税区","lat":34.3969028,"lng":109.0390626,"rawLat":34.3969028,"rawLng":109.0390626,"transferKey":"保税区","platformKey":"7719093:0:保税区","osmRefs":["node/2977155119"]},{"name":"新筑","lat":34.3843167,"lng":109.037811,"rawLat":34.3843167,"rawLng":109.037811,"transferKey":"新筑","platformKey":"7719093:1:新筑","osmRefs":["node/5218356746"]},{"name":"双寨","lat":34.3737416,"lng":109.0361506,"rawLat":34.3737416,"rawLng":109.0361506,"transferKey":"双寨","platformKey":"7719093:2:双寨","osmRefs":["node/7411636714"]},{"name":"国际港务区","lat":34.3623412,"lng":109.03435,"rawLat":34.3623412,"rawLng":109.03435,"transferKey":"国际港务区","platformKey":"7719093:3:国际港务区","osmRefs":["node/2977155120"]},{"name":"务庄","lat":34.3465525,"lng":109.0424546,"rawLat":34.3465525,"rawLng":109.0424546,"transferKey":"务庄","platformKey":"7719093:4:务庄","osmRefs":["node/11228576281"]},{"name":"香湖湾","lat":34.3314114,"lng":109.0472785,"rawLat":34.3314114,"rawLng":109.0472785,"transferKey":"香湖湾","platformKey":"7719093:5:香湖湾","osmRefs":["node/9335653682"]},{"name":"浐灞中心","lat":34.3182537,"lng":109.0412605,"rawLat":34.3182537,"rawLng":109.0412605,"transferKey":"浐灞中心","platformKey":"7719093:6:浐灞中心","osmRefs":["node/11228576258"]},{"name":"桃花潭","lat":34.3125017,"lng":109.0282017,"rawLat":34.3125017,"rawLng":109.0282017,"transferKey":"桃花潭","platformKey":"7719093:7:桃花潭","osmRefs":["node/2977172944"]},{"name":"鱼化寨","lat":34.2395379,"lng":108.8441315,"rawLat":34.2395379,"rawLng":108.8441315,"transferKey":"鱼化寨","platformKey":"7719093:8:鱼化寨","osmRefs":["node/2972583313"]},{"name":"丈八北路","lat":34.2389919,"lng":108.8685031,"rawLat":34.2389919,"rawLng":108.8685031,"transferKey":"丈八北路","platformKey":"7719093:9:丈八北路","osmRefs":["node/2977172957"]},{"name":"延平门","lat":34.2388152,"lng":108.8826219,"rawLat":34.2388152,"rawLng":108.8826219,"transferKey":"延平门","platformKey":"7719093:10:延平门","osmRefs":["node/2977172956"]},{"name":"科技路","lat":34.2328604,"lng":108.899566,"rawLat":34.2328604,"rawLng":108.899566,"transferKey":"科技路","platformKey":"7719093:11:科技路","osmRefs":["node/9006301333"]},{"name":"太白南路","lat":34.2269807,"lng":108.9127612,"rawLat":34.2269807,"rawLng":108.9127612,"transferKey":"太白南路","platformKey":"7719093:12:太白南路","osmRefs":["node/2972402840"]},{"name":"吉祥村","lat":34.2240625,"lng":108.9287189,"rawLat":34.2240625,"rawLng":108.9287189,"transferKey":"吉祥村","platformKey":"7719093:13:吉祥村","osmRefs":["node/2972402836"]},{"name":"小寨","lat":34.2243289,"lng":108.9427833,"rawLat":34.2243289,"rawLng":108.9427833,"transferKey":"小寨","platformKey":"7719093:14:小寨","osmRefs":["node/9554045517"]},{"name":"大雁塔","lat":34.2243534,"lng":108.9592757,"rawLat":34.2243534,"rawLng":108.9592757,"transferKey":"大雁塔","platformKey":"7719093:15:大雁塔","osmRefs":["node/9443169358"]},{"name":"北池头","lat":34.2252645,"lng":108.9725038,"rawLat":34.2252645,"rawLng":108.9725038,"transferKey":"北池头","platformKey":"7719093:16:北池头","osmRefs":["node/2977172952"]},{"name":"青龙寺","lat":34.232458,"lng":108.9896302,"rawLat":34.232458,"rawLng":108.9896302,"transferKey":"青龙寺","platformKey":"7719093:17:青龙寺","osmRefs":["node/5218356752"]},{"name":"延兴门","lat":34.245486,"lng":108.9919741,"rawLat":34.245486,"rawLng":108.9919741,"transferKey":"延兴门","platformKey":"7719093:18:延兴门","osmRefs":["node/2972400017"]},{"name":"咸宁路","lat":34.2526135,"lng":108.9917907,"rawLat":34.2526135,"rawLng":108.9917907,"transferKey":"咸宁路","platformKey":"7719093:19:咸宁路","osmRefs":["node/10312280498"]},{"name":"长乐公园","lat":34.2622664,"lng":108.9914519,"rawLat":34.2622664,"rawLng":108.9914519,"transferKey":"长乐公园","platformKey":"7719093:20:长乐公园","osmRefs":["node/2972400013"]},{"name":"通化门","lat":34.2709902,"lng":108.990632,"rawLat":34.2709902,"rawLng":108.990632,"transferKey":"通化门","platformKey":"7719093:21:通化门","osmRefs":["node/9591821089"]},{"name":"胡家庙","lat":34.2789001,"lng":108.9907576,"rawLat":34.2789001,"rawLng":108.9907576,"transferKey":"胡家庙","platformKey":"7719093:22:胡家庙","osmRefs":["node/2977172948"]},{"name":"石家街","lat":34.2925702,"lng":108.9909371,"rawLat":34.2925702,"rawLng":108.9909371,"transferKey":"石家街","platformKey":"7719093:23:石家街","osmRefs":["node/2977172947"]},{"name":"辛家庙","lat":34.3066245,"lng":108.9907366,"rawLat":34.3066245,"rawLng":108.9907366,"transferKey":"辛家庙","platformKey":"7719093:24:辛家庙","osmRefs":["node/2972399999"]},{"name":"广泰门","lat":34.3121784,"lng":109.0083824,"rawLat":34.3121784,"rawLng":109.0083824,"transferKey":"广泰门","platformKey":"7719093:25:广泰门","osmRefs":["node/2972399991"]}],"waypoints":[{"lat":34.39392,"lng":109.038879,"segIdx":0,"order":0},{"lat":34.3911135,"lng":109.0386268,"segIdx":0,"order":1},{"lat":34.3837857,"lng":109.0377123,"segIdx":1,"order":0},{"lat":34.3773318,"lng":109.036723,"segIdx":1,"order":1},{"lat":34.3729649,"lng":109.0360265,"segIdx":2,"order":0},{"lat":34.3629845,"lng":109.0344494,"segIdx":2,"order":1},{"lat":34.3617954,"lng":109.0342547,"segIdx":3,"order":0},{"lat":34.3531952,"lng":109.0329487,"segIdx":3,"order":1},{"lat":34.3515309,"lng":109.0333233,"segIdx":3,"order":2},{"lat":34.3499814,"lng":109.0349515,"segIdx":3,"order":3},{"lat":34.3468902,"lng":109.0416812,"segIdx":3,"order":4},{"lat":34.3462799,"lng":109.0430688,"segIdx":4,"order":0},{"lat":34.3434042,"lng":109.0490842,"segIdx":4,"order":1},{"lat":34.3413977,"lng":109.0507645,"segIdx":4,"order":2},{"lat":34.3365155,"lng":109.0504147,"segIdx":4,"order":3},{"lat":34.332007,"lng":109.0476614,"segIdx":4,"order":4},{"lat":34.3308458,"lng":109.0468898,"segIdx":5,"order":0},{"lat":34.3200272,"lng":109.0419671,"segIdx":5,"order":1},{"lat":34.3173931,"lng":109.040889,"segIdx":6,"order":0},{"lat":34.3132752,"lng":109.0383978,"segIdx":6,"order":1},{"lat":34.3125827,"lng":109.0364729,"segIdx":6,"order":2},{"lat":34.312557,"lng":109.032789,"segIdx":6,"order":3},{"lat":34.3124935,"lng":109.0273594,"segIdx":7,"order":0},{"lat":34.3124861,"lng":109.0202104,"segIdx":7,"order":1},{"lat":34.2396165,"lng":108.8414002,"segIdx":7,"order":2},{"lat":34.2395652,"lng":108.8431823,"segIdx":7,"order":3},{"lat":34.2395156,"lng":108.8449037,"segIdx":8,"order":0},{"lat":34.2390597,"lng":108.8638237,"segIdx":8,"order":1},{"lat":34.2389755,"lng":108.8695487,"segIdx":9,"order":0},{"lat":34.2388237,"lng":108.8818417,"segIdx":9,"order":1},{"lat":34.2388087,"lng":108.8832841,"segIdx":10,"order":0},{"lat":34.238685,"lng":108.8865601,"segIdx":10,"order":1},{"lat":34.2362272,"lng":108.8921462,"segIdx":10,"order":2},{"lat":34.2312184,"lng":108.9032967,"segIdx":11,"order":0},{"lat":34.227249,"lng":108.9121619,"segIdx":11,"order":1},{"lat":34.2261482,"lng":108.9146134,"segIdx":12,"order":0},{"lat":34.2244998,"lng":108.918478,"segIdx":12,"order":1},{"lat":34.2240566,"lng":108.9271125,"segIdx":12,"order":2},{"lat":34.2240639,"lng":108.9297988,"segIdx":13,"order":0},{"lat":34.2243268,"lng":108.9418754,"segIdx":13,"order":1},{"lat":34.224328,"lng":108.944985,"segIdx":14,"order":0},{"lat":34.2243442,"lng":108.9513889,"segIdx":14,"order":1},{"lat":34.2243582,"lng":108.9603783,"segIdx":15,"order":0},{"lat":34.2249716,"lng":108.9718062,"segIdx":15,"order":1},{"lat":34.225953,"lng":108.9741161,"segIdx":16,"order":0},{"lat":34.2291816,"lng":108.981831,"segIdx":16,"order":1},{"lat":34.2329095,"lng":108.9907283,"segIdx":17,"order":0},{"lat":34.2348288,"lng":108.9947618,"segIdx":17,"order":1},{"lat":34.2374465,"lng":108.9963823,"segIdx":17,"order":2},{"lat":34.2398179,"lng":108.9951722,"segIdx":17,"order":3},{"lat":34.2417501,"lng":108.9925547,"segIdx":17,"order":4},{"lat":34.2445736,"lng":108.9920205,"segIdx":17,"order":5},{"lat":34.2461361,"lng":108.9919355,"segIdx":18,"order":0},{"lat":34.251856,"lng":108.9918048,"segIdx":18,"order":1},{"lat":34.2538731,"lng":108.9917697,"segIdx":19,"order":0},{"lat":34.2618102,"lng":108.9916922,"segIdx":19,"order":1},{"lat":34.2629751,"lng":108.9910593,"segIdx":20,"order":0},{"lat":34.2679292,"lng":108.9905745,"segIdx":20,"order":1},{"lat":34.2743142,"lng":108.9906741,"segIdx":21,"order":0},{"lat":34.2765551,"lng":108.9907608,"segIdx":21,"order":1},{"lat":34.279576,"lng":108.9907595,"segIdx":22,"order":0},{"lat":34.2920697,"lng":108.9909391,"segIdx":22,"order":1},{"lat":34.2932548,"lng":108.9909341,"segIdx":23,"order":0},{"lat":34.3027208,"lng":108.9907411,"segIdx":23,"order":1},{"lat":34.3088574,"lng":108.990768,"segIdx":24,"order":0},{"lat":34.310769,"lng":108.9912769,"segIdx":24,"order":1},{"lat":34.3117602,"lng":108.9928744,"segIdx":24,"order":2},{"lat":34.3121586,"lng":109.0067663,"segIdx":24,"order":3}]},{"relationId":9807756,"key":"西安地铁|4","name":"西安地铁4号线：西安北站→航天新城","ref":"4","network":"西安地铁","route":"subway","color":"#39b09e","isLoop":false,"loopMode":"","loopReason":"","loopTerminalDistanceM":27209,"stations":[{"name":"西安北站","lat":34.3809497,"lng":108.9341649,"rawLat":34.3809497,"rawLng":108.9341649,"transferKey":"西安北","platformKey":"9807756:0:西安北","osmRefs":["node/8964619146"]},{"name":"元鼎路","lat":34.3688796,"lng":108.9250408,"rawLat":34.3688796,"rawLng":108.9250408,"transferKey":"元鼎路","platformKey":"9807756:1:元鼎路","osmRefs":["node/6164692558"]},{"name":"凤城十二路","lat":34.3606924,"lng":108.9250303,"rawLat":34.3606924,"rawLng":108.9250303,"transferKey":"凤城十二路","platformKey":"9807756:2:凤城十二路","osmRefs":["node/6164692562"]},{"name":"凤城九路","lat":34.349005,"lng":108.9250408,"rawLat":34.349005,"rawLng":108.9250408,"transferKey":"凤城九路","platformKey":"9807756:3:凤城九路","osmRefs":["node/6164692565"]},{"name":"文景路","lat":34.3425241,"lng":108.9320778,"rawLat":34.3425241,"rawLng":108.9320778,"transferKey":"文景路","platformKey":"9807756:4:文景路","osmRefs":["node/6164692576"]},{"name":"行政中心","lat":34.3425594,"lng":108.9425635,"rawLat":34.3425594,"rawLng":108.9425635,"transferKey":"行政中心","platformKey":"9807756:5:行政中心","osmRefs":["node/1626880538"]},{"name":"市中医医院","lat":34.3425592,"lng":108.9557157,"rawLat":34.3425592,"rawLng":108.9557157,"transferKey":"市中医医院","platformKey":"9807756:6:市中医医院","osmRefs":["node/6164692579"]},{"name":"常青路","lat":34.3369369,"lng":108.9668106,"rawLat":34.3369369,"rawLng":108.9668106,"transferKey":"常青路","platformKey":"9807756:7:常青路","osmRefs":["node/6164695189"]},{"name":"百花村","lat":34.3280127,"lng":108.9668048,"rawLat":34.3280127,"rawLng":108.9668048,"transferKey":"百花村","platformKey":"9807756:8:百花村","osmRefs":["node/6164695192"]},{"name":"余家寨","lat":34.3186075,"lng":108.9667916,"rawLat":34.3186075,"rawLng":108.9667916,"transferKey":"余家寨","platformKey":"9807756:9:余家寨","osmRefs":["node/6164695195"]},{"name":"大明宫北","lat":34.3095732,"lng":108.9667944,"rawLat":34.3095732,"rawLng":108.9667944,"transferKey":"大明宫北","platformKey":"9807756:10:大明宫北","osmRefs":["node/6164695198"]},{"name":"大明宫","lat":34.2982161,"lng":108.9667038,"rawLat":34.2982161,"rawLng":108.9667038,"transferKey":"大明宫","platformKey":"9807756:11:大明宫","osmRefs":["node/6164695202"]},{"name":"含元殿","lat":34.2891459,"lng":108.9666846,"rawLat":34.2891459,"rawLng":108.9666846,"transferKey":"含元殿","platformKey":"9807756:12:含元殿","osmRefs":["node/6164695204"]},{"name":"西安站","lat":34.2798324,"lng":108.960845,"rawLat":34.2798324,"rawLng":108.960845,"transferKey":"西安","platformKey":"9807756:13:西安","osmRefs":["node/6164695222"]},{"name":"五路口","lat":34.2711309,"lng":108.9581912,"rawLat":34.2711309,"rawLng":108.9581912,"transferKey":"五路口","platformKey":"9807756:14:五路口","osmRefs":["node/9591752584"]},{"name":"大差市","lat":34.2610583,"lng":108.9584315,"rawLat":34.2610583,"rawLng":108.9584315,"transferKey":"大差市","platformKey":"9807756:15:大差市","osmRefs":["node/6164695231"]},{"name":"和平门","lat":34.2513987,"lng":108.9586099,"rawLat":34.2513987,"rawLng":108.9586099,"transferKey":"和平门","platformKey":"9807756:16:和平门","osmRefs":["node/6164695238"]},{"name":"建筑科技大学·李家村","lat":34.2427655,"lng":108.9588495,"rawLat":34.2427655,"rawLng":108.9588495,"transferKey":"建筑科技大学·李家村","platformKey":"9807756:17:建筑科技大学·李家村","osmRefs":["node/9429850185"]},{"name":"西安科技大学","lat":34.2349954,"lng":108.9590007,"rawLat":34.2349954,"rawLng":108.9590007,"transferKey":"西安科技大学","platformKey":"9807756:18:西安科技大学","osmRefs":["node/6164695245"]},{"name":"大雁塔","lat":34.2247243,"lng":108.9591907,"rawLat":34.2247243,"rawLng":108.9591907,"transferKey":"大雁塔","platformKey":"9807756:19:大雁塔","osmRefs":["node/9334033646"]},{"name":"大唐芙蓉园","lat":34.2112641,"lng":108.9663424,"rawLat":34.2112641,"rawLng":108.9663424,"transferKey":"大唐芙蓉园","platformKey":"9807756:20:大唐芙蓉园","osmRefs":["node/11217698195"]},{"name":"曲江池西","lat":34.1989785,"lng":108.9702161,"rawLat":34.1989785,"rawLng":108.9702161,"transferKey":"曲江池西","platformKey":"9807756:21:曲江池西","osmRefs":["node/6164695268"]},{"name":"金滹沱","lat":34.1820837,"lng":108.9705189,"rawLat":34.1820837,"rawLng":108.9705189,"transferKey":"金滹沱","platformKey":"9807756:22:金滹沱","osmRefs":["node/6164695273"]},{"name":"航天大道","lat":34.1722206,"lng":108.9697559,"rawLat":34.1722206,"rawLng":108.9697559,"transferKey":"航天大道","platformKey":"9807756:23:航天大道","osmRefs":["node/6164695279"]},{"name":"飞天路","lat":34.1639632,"lng":108.969758,"rawLat":34.1639632,"rawLng":108.969758,"transferKey":"飞天路","platformKey":"9807756:24:飞天路","osmRefs":["node/6164695281"]},{"name":"东长安街","lat":34.1557655,"lng":108.9697581,"rawLat":34.1557655,"rawLng":108.9697581,"transferKey":"东长安街","platformKey":"9807756:25:东长安街","osmRefs":["node/6164695283"]},{"name":"神舟大道","lat":34.1440445,"lng":108.9788651,"rawLat":34.1440445,"rawLng":108.9788651,"transferKey":"神舟大道","platformKey":"9807756:26:神舟大道","osmRefs":["node/6164695395"]},{"name":"航天东路","lat":34.144015,"lng":108.9921905,"rawLat":34.144015,"rawLng":108.9921905,"transferKey":"航天东路","platformKey":"9807756:27:航天东路","osmRefs":["node/6164695396"]},{"name":"航天新城","lat":34.1439777,"lng":109.0079536,"rawLat":34.1439777,"rawLng":109.0079536,"transferKey":"航天新城","platformKey":"9807756:28:航天新城","osmRefs":["node/6164695398"]}],"waypoints":[{"lat":34.3807564,"lng":108.9334333,"segIdx":0,"order":0},{"lat":34.3790207,"lng":108.9267143,"segIdx":0,"order":1},{"lat":34.3761681,"lng":108.92509,"segIdx":0,"order":2},{"lat":34.3720963,"lng":108.9249472,"segIdx":0,"order":3},{"lat":34.3667655,"lng":108.9250751,"segIdx":1,"order":0},{"lat":34.3643938,"lng":108.9250717,"segIdx":1,"order":1},{"lat":34.3593513,"lng":108.9250336,"segIdx":2,"order":0},{"lat":34.3508701,"lng":108.9250615,"segIdx":2,"order":1},{"lat":34.3480359,"lng":108.9251035,"segIdx":3,"order":0},{"lat":34.3444619,"lng":108.9271206,"segIdx":3,"order":1},{"lat":34.3425149,"lng":108.9308042,"segIdx":3,"order":2},{"lat":34.3425598,"lng":108.9459712,"segIdx":5,"order":0},{"lat":34.3425531,"lng":108.9599065,"segIdx":6,"order":0},{"lat":34.3415236,"lng":108.9656506,"segIdx":6,"order":1},{"lat":34.3395416,"lng":108.9668554,"segIdx":6,"order":2},{"lat":34.3334856,"lng":108.9668032,"segIdx":7,"order":0},{"lat":34.3307262,"lng":108.9668368,"segIdx":7,"order":1},{"lat":34.3240938,"lng":108.9667786,"segIdx":8,"order":0},{"lat":34.3207738,"lng":108.9668143,"segIdx":8,"order":1},{"lat":34.3151691,"lng":108.9667705,"segIdx":9,"order":0},{"lat":34.3119589,"lng":108.9667786,"segIdx":9,"order":1},{"lat":34.3075902,"lng":108.9667351,"segIdx":10,"order":0},{"lat":34.3006618,"lng":108.966738,"segIdx":10,"order":1},{"lat":34.2952364,"lng":108.966718,"segIdx":11,"order":0},{"lat":34.2874716,"lng":108.9666942,"segIdx":12,"order":0},{"lat":34.2834093,"lng":108.9663326,"segIdx":12,"order":1},{"lat":34.2811854,"lng":108.9622747,"segIdx":12,"order":2},{"lat":34.278457,"lng":108.9593685,"segIdx":13,"order":0},{"lat":34.2769527,"lng":108.9581191,"segIdx":13,"order":1},{"lat":34.273093,"lng":108.958145,"segIdx":13,"order":2},{"lat":34.2699855,"lng":108.9582255,"segIdx":14,"order":0},{"lat":34.2622291,"lng":108.9584026,"segIdx":14,"order":1},{"lat":34.2605632,"lng":108.9584358,"segIdx":15,"order":0},{"lat":34.2520795,"lng":108.9585988,"segIdx":15,"order":1},{"lat":34.2476469,"lng":108.9586316,"segIdx":16,"order":0},{"lat":34.2437871,"lng":108.9588176,"segIdx":16,"order":1},{"lat":34.2421709,"lng":108.9588467,"segIdx":17,"order":0},{"lat":34.2371896,"lng":108.9589583,"segIdx":17,"order":1},{"lat":34.2320299,"lng":108.9590758,"segIdx":18,"order":0},{"lat":34.2267768,"lng":108.9591435,"segIdx":18,"order":1},{"lat":34.2240727,"lng":108.9593056,"segIdx":19,"order":0},{"lat":34.2213167,"lng":108.9599821,"segIdx":19,"order":1},{"lat":34.2194554,"lng":108.9642166,"segIdx":19,"order":2},{"lat":34.218124,"lng":108.965565,"segIdx":19,"order":3},{"lat":34.2164425,"lng":108.9658409,"segIdx":19,"order":4},{"lat":34.2137211,"lng":108.9647436,"segIdx":19,"order":5},{"lat":34.2125225,"lng":108.9652968,"segIdx":19,"order":6},{"lat":34.2106763,"lng":108.9668317,"segIdx":20,"order":0},{"lat":34.2066118,"lng":108.970247,"segIdx":20,"order":1},{"lat":34.1995772,"lng":108.9701616,"segIdx":20,"order":2},{"lat":34.1983339,"lng":108.9702886,"segIdx":21,"order":0},{"lat":34.1852103,"lng":108.9705585,"segIdx":21,"order":1},{"lat":34.1799941,"lng":108.9704995,"segIdx":22,"order":0},{"lat":34.1743637,"lng":108.9697547,"segIdx":22,"order":1},{"lat":34.1716793,"lng":108.9697548,"segIdx":23,"order":0},{"lat":34.1691173,"lng":108.9697495,"segIdx":23,"order":1},{"lat":34.1604585,"lng":108.9697676,"segIdx":24,"order":0},{"lat":34.155177,"lng":108.9697591,"segIdx":25,"order":0},{"lat":34.1492663,"lng":108.9697495,"segIdx":25,"order":1},{"lat":34.1477036,"lng":108.9703718,"segIdx":25,"order":2},{"lat":34.1449155,"lng":108.9729574,"segIdx":25,"order":3},{"lat":34.1440514,"lng":108.9768224,"segIdx":25,"order":4},{"lat":34.1440221,"lng":108.9956209,"segIdx":27,"order":0},{"lat":34.1439796,"lng":109.0071786,"segIdx":27,"order":1}]},{"relationId":12925431,"key":"西安地铁|5","name":"西安地铁5号线：创新港→西安东站","ref":"5","network":"西安地铁","route":"subway","color":"#a6e35f","isLoop":false,"loopMode":"","loopReason":"","loopTerminalDistanceM":37336,"stations":[{"name":"创新港","lat":34.2513636,"lng":108.6527061,"rawLat":34.2513636,"rawLng":108.6527061,"transferKey":"创新港","platformKey":"12925431:0:创新港","osmRefs":["node/9032386274"]},{"name":"创新港东","lat":34.259728,"lng":108.662171,"rawLat":34.259728,"rawLng":108.662171,"transferKey":"创新港东","platformKey":"12925431:1:创新港东","osmRefs":["node/8898747460"]},{"name":"翱翔小镇","lat":34.270178,"lng":108.6760248,"rawLat":34.270178,"rawLng":108.6760248,"transferKey":"翱翔小镇","platformKey":"12925431:2:翱翔小镇","osmRefs":["node/8898928339"]},{"name":"钓台","lat":34.2702138,"lng":108.6859313,"rawLat":34.2702138,"rawLng":108.6859313,"transferKey":"钓台","platformKey":"12925431:3:钓台","osmRefs":["node/8898928338"]},{"name":"沣西文化公园","lat":34.2702304,"lng":108.6966124,"rawLat":34.2702304,"rawLng":108.6966124,"transferKey":"沣西文化公园","platformKey":"12925431:4:沣西文化公园","osmRefs":["node/8898928311"]},{"name":"东马坊","lat":34.2627167,"lng":108.706121,"rawLat":34.2627167,"rawLng":108.706121,"transferKey":"东马坊","platformKey":"12925431:5:东马坊","osmRefs":["node/6898529981"]},{"name":"高桥","lat":34.2424504,"lng":108.7129461,"rawLat":34.2424504,"rawLng":108.7129461,"transferKey":"高桥","platformKey":"12925431:6:高桥","osmRefs":["node/8898928290"]},{"name":"文教园","lat":34.2421464,"lng":108.7225295,"rawLat":34.2421464,"rawLng":108.7225295,"transferKey":"文教园","platformKey":"12925431:7:文教园","osmRefs":["node/8898928283"]},{"name":"欢乐谷","lat":34.2463722,"lng":108.7436547,"rawLat":34.2463722,"rawLng":108.7436547,"transferKey":"欢乐谷","platformKey":"12925431:8:欢乐谷","osmRefs":["node/8898927912"]},{"name":"镐京","lat":34.2463842,"lng":108.7542048,"rawLat":34.2463842,"rawLng":108.7542048,"transferKey":"镐京","platformKey":"12925431:9:镐京","osmRefs":["node/8898927895"]},{"name":"复兴大道南","lat":34.2464058,"lng":108.7655698,"rawLat":34.2464058,"rawLng":108.7655698,"transferKey":"复兴大道南","platformKey":"12925431:10:复兴大道南","osmRefs":["node/8898927868"]},{"name":"斗门","lat":34.2464543,"lng":108.786016,"rawLat":34.2464543,"rawLng":108.786016,"transferKey":"斗门","platformKey":"12925431:11:斗门","osmRefs":["node/8898927841"]},{"name":"王寺","lat":34.2465625,"lng":108.800852,"rawLat":34.2465625,"rawLng":108.800852,"transferKey":"王寺","platformKey":"12925431:12:王寺","osmRefs":["node/8898927839"]},{"name":"阿房宫南","lat":34.2539727,"lng":108.8208209,"rawLat":34.2539727,"rawLng":108.8208209,"transferKey":"阿房宫南","platformKey":"12925431:13:阿房宫南","osmRefs":["node/8898927815"]},{"name":"石桥立交","lat":34.2539164,"lng":108.8295178,"rawLat":34.2539164,"rawLng":108.8295178,"transferKey":"石桥立交","platformKey":"12925431:14:石桥立交","osmRefs":["node/8898927808"]},{"name":"西窑头","lat":34.2538661,"lng":108.8479765,"rawLat":34.2538661,"rawLng":108.8479765,"transferKey":"西窑头","platformKey":"12925431:15:西窑头","osmRefs":["node/8898927390"]},{"name":"汉城南路","lat":34.2538765,"lng":108.8671806,"rawLat":34.2538765,"rawLng":108.8671806,"transferKey":"汉城南路","platformKey":"12925431:16:汉城南路","osmRefs":["node/8898927798"]},{"name":"金光门","lat":34.2537267,"lng":108.8837508,"rawLat":34.2537267,"rawLng":108.8837508,"transferKey":"金光门","platformKey":"12925431:17:金光门","osmRefs":["node/8898927395"]},{"name":"丰庆公园","lat":34.2477462,"lng":108.8953456,"rawLat":34.2477462,"rawLng":108.8953456,"transferKey":"丰庆公园","platformKey":"12925431:18:丰庆公园","osmRefs":["node/8898927792"]},{"name":"西北工业大学","lat":34.2426386,"lng":108.9060794,"rawLat":34.2426386,"rawLng":108.9060794,"transferKey":"西北工业大学","platformKey":"12925431:19:西北工业大学","osmRefs":["node/7171518644"]},{"name":"边家村","lat":34.2427683,"lng":108.9188348,"rawLat":34.2427683,"rawLng":108.9188348,"transferKey":"边家村","platformKey":"12925431:20:边家村","osmRefs":["node/8898927783"]},{"name":"省人民医院·黄雁村","lat":34.2427972,"lng":108.9283995,"rawLat":34.2427972,"rawLng":108.9283995,"transferKey":"省人民医院·黄雁村","platformKey":"12925431:21:省人民医院·黄雁村","osmRefs":["node/8898927766"]},{"name":"南稍门","lat":34.2427527,"lng":108.9412437,"rawLat":34.2427527,"rawLng":108.9412437,"transferKey":"南稍门","platformKey":"12925431:22:南稍门","osmRefs":["node/2603038449"]},{"name":"文艺路","lat":34.2427469,"lng":108.9507382,"rawLat":34.2427469,"rawLng":108.9507382,"transferKey":"文艺路","platformKey":"12925431:23:文艺路","osmRefs":["node/8898927756"]},{"name":"建筑科技大学·李家村","lat":34.2427295,"lng":108.958879,"rawLat":34.2427295,"rawLng":108.958879,"transferKey":"建筑科技大学·李家村","platformKey":"12925431:24:建筑科技大学·李家村","osmRefs":["node/7959561661"]},{"name":"太乙路","lat":34.2427687,"lng":108.9690807,"rawLat":34.2427687,"rawLng":108.9690807,"transferKey":"太乙路","platformKey":"12925431:25:太乙路","osmRefs":["node/7411452225"]},{"name":"雁翔路北口","lat":34.2398488,"lng":108.9843828,"rawLat":34.2398488,"rawLng":108.9843828,"transferKey":"雁翔路北口","platformKey":"12925431:26:雁翔路北口","osmRefs":["node/8898927434"]},{"name":"青龙寺","lat":34.2322708,"lng":108.9890941,"rawLat":34.2322708,"rawLng":108.9890941,"transferKey":"青龙寺","platformKey":"12925431:27:青龙寺","osmRefs":["node/9334033642"]},{"name":"理工大曲江校区","lat":34.2202058,"lng":108.9969337,"rawLat":34.2202058,"rawLng":108.9969337,"transferKey":"理工大曲江校区","platformKey":"12925431:28:理工大曲江校区","osmRefs":["node/8898927605"]},{"name":"黄渠头","lat":34.2165258,"lng":109.0089488,"rawLat":34.2165258,"rawLng":109.0089488,"transferKey":"黄渠头","platformKey":"12925431:29:黄渠头","osmRefs":["node/8898927600"]},{"name":"马腾空","lat":34.220736,"lng":109.0217583,"rawLat":34.220736,"rawLng":109.0217583,"transferKey":"马腾空","platformKey":"12925431:30:马腾空","osmRefs":["node/8898927574"]},{"name":"月登阁","lat":34.2214016,"lng":109.0324363,"rawLat":34.2214016,"rawLng":109.0324363,"transferKey":"月登阁","platformKey":"12925431:31:月登阁","osmRefs":["node/11377105504"]},{"name":"雁鸣湖","lat":34.2236654,"lng":109.0458517,"rawLat":34.2236654,"rawLng":109.0458517,"transferKey":"雁鸣湖","platformKey":"12925431:32:雁鸣湖","osmRefs":["node/12199342781"]},{"name":"西安东站","lat":34.2154335,"lng":109.0565031,"rawLat":34.2154335,"rawLng":109.0565031,"transferKey":"西安东","platformKey":"12925431:33:西安东","osmRefs":["node/13983518587"]}],"waypoints":[{"lat":34.2513728,"lng":108.6535011,"segIdx":0,"order":0},{"lat":34.2516067,"lng":108.6569458,"segIdx":0,"order":1},{"lat":34.2529616,"lng":108.6596183,"segIdx":0,"order":2},{"lat":34.2546254,"lng":108.6608108,"segIdx":0,"order":3},{"lat":34.2590553,"lng":108.6620309,"segIdx":0,"order":4},{"lat":34.2602718,"lng":108.6623199,"segIdx":1,"order":0},{"lat":34.2665764,"lng":108.6638384,"segIdx":1,"order":1},{"lat":34.2688817,"lng":108.6657689,"segIdx":1,"order":2},{"lat":34.2701091,"lng":108.6686778,"segIdx":1,"order":3},{"lat":34.2701702,"lng":108.6752574,"segIdx":1,"order":4},{"lat":34.27018,"lng":108.676789,"segIdx":2,"order":0},{"lat":34.2701987,"lng":108.6851374,"segIdx":2,"order":1},{"lat":34.2701945,"lng":108.686641,"segIdx":3,"order":0},{"lat":34.2702186,"lng":108.6958504,"segIdx":3,"order":1},{"lat":34.2702129,"lng":108.6973527,"segIdx":4,"order":0},{"lat":34.2702392,"lng":108.7024337,"segIdx":4,"order":1},{"lat":34.2690138,"lng":108.7050375,"segIdx":4,"order":2},{"lat":34.2670673,"lng":108.7060757,"segIdx":4,"order":3},{"lat":34.2633924,"lng":108.7061002,"segIdx":4,"order":4},{"lat":34.262091,"lng":108.706124,"segIdx":5,"order":0},{"lat":34.2566015,"lng":108.7081158,"segIdx":5,"order":1},{"lat":34.2497795,"lng":108.7063168,"segIdx":5,"order":2},{"lat":34.2473014,"lng":108.706452,"segIdx":5,"order":3},{"lat":34.2438384,"lng":108.7080793,"segIdx":5,"order":4},{"lat":34.2424192,"lng":108.7117358,"segIdx":5,"order":5},{"lat":34.242429,"lng":108.7140761,"segIdx":6,"order":0},{"lat":34.2422954,"lng":108.7218351,"segIdx":6,"order":1},{"lat":34.2419073,"lng":108.7232728,"segIdx":7,"order":0},{"lat":34.2423009,"lng":108.7274101,"segIdx":7,"order":1},{"lat":34.2461181,"lng":108.7323524,"segIdx":7,"order":2},{"lat":34.2463782,"lng":108.741753,"segIdx":7,"order":3},{"lat":34.2463839,"lng":108.7492257,"segIdx":8,"order":0},{"lat":34.2463842,"lng":108.7535455,"segIdx":8,"order":1},{"lat":34.24639,"lng":108.7639507,"segIdx":9,"order":0},{"lat":34.2463888,"lng":108.7667728,"segIdx":10,"order":0},{"lat":34.2464372,"lng":108.7832259,"segIdx":10,"order":1},{"lat":34.2464519,"lng":108.7868399,"segIdx":11,"order":0},{"lat":34.2464639,"lng":108.799645,"segIdx":11,"order":1},{"lat":34.2467632,"lng":108.802915,"segIdx":12,"order":0},{"lat":34.2478382,"lng":108.8048556,"segIdx":12,"order":1},{"lat":34.2514077,"lng":108.8050482,"segIdx":12,"order":2},{"lat":34.2531533,"lng":108.8067875,"segIdx":12,"order":3},{"lat":34.2539623,"lng":108.8198537,"segIdx":12,"order":4},{"lat":34.2539794,"lng":108.821559,"segIdx":13,"order":0},{"lat":34.2539062,"lng":108.8288547,"segIdx":13,"order":1},{"lat":34.2538568,"lng":108.8332061,"segIdx":14,"order":0},{"lat":34.2538738,"lng":108.8467658,"segIdx":14,"order":1},{"lat":34.2538927,"lng":108.850058,"segIdx":15,"order":0},{"lat":34.2538695,"lng":108.8665739,"segIdx":15,"order":1},{"lat":34.2538983,"lng":108.8710686,"segIdx":16,"order":0},{"lat":34.2537232,"lng":108.8831082,"segIdx":16,"order":1},{"lat":34.2537242,"lng":108.8844103,"segIdx":17,"order":0},{"lat":34.2538214,"lng":108.890122,"segIdx":17,"order":1},{"lat":34.2530304,"lng":108.8928038,"segIdx":17,"order":2},{"lat":34.2519249,"lng":108.8943375,"segIdx":17,"order":3},{"lat":34.2503283,"lng":108.8950543,"segIdx":17,"order":4},{"lat":34.2470498,"lng":108.8954409,"segIdx":18,"order":0},{"lat":34.2447321,"lng":108.8965456,"segIdx":18,"order":1},{"lat":34.2422637,"lng":108.9021935,"segIdx":18,"order":2},{"lat":34.2423719,"lng":108.9044387,"segIdx":18,"order":3},{"lat":34.2426877,"lng":108.9068975,"segIdx":19,"order":0},{"lat":34.2426819,"lng":108.9075862,"segIdx":19,"order":1},{"lat":34.2427943,"lng":108.9292307,"segIdx":21,"order":0},{"lat":34.2427321,"lng":108.9576593,"segIdx":23,"order":0},{"lat":34.2427202,"lng":108.9658326,"segIdx":24,"order":0},{"lat":34.2427167,"lng":108.981327,"segIdx":25,"order":0},{"lat":34.2419581,"lng":108.9830101,"segIdx":25,"order":1},{"lat":34.2390582,"lng":108.9848722,"segIdx":26,"order":0},{"lat":34.235185,"lng":108.9871922,"segIdx":26,"order":1},{"lat":34.2285095,"lng":108.9914409,"segIdx":27,"order":0},{"lat":34.221076,"lng":108.9963773,"segIdx":27,"order":1},{"lat":34.2193073,"lng":108.9975082,"segIdx":28,"order":0},{"lat":34.2174206,"lng":108.9985809,"segIdx":28,"order":1},{"lat":34.2163178,"lng":109.0004702,"segIdx":28,"order":2},{"lat":34.2151694,"lng":109.0050778,"segIdx":28,"order":3},{"lat":34.2155616,"lng":109.007011,"segIdx":28,"order":4},{"lat":34.2181626,"lng":109.0125777,"segIdx":29,"order":0},{"lat":34.2205899,"lng":109.0209948,"segIdx":29,"order":1},{"lat":34.2208783,"lng":109.0224723,"segIdx":30,"order":0},{"lat":34.2212873,"lng":109.0256285,"segIdx":30,"order":1},{"lat":34.2218456,"lng":109.037973,"segIdx":31,"order":0},{"lat":34.2234203,"lng":109.0450674,"segIdx":31,"order":1},{"lat":34.2240745,"lng":109.0471665,"segIdx":32,"order":0},{"lat":34.2244698,"lng":109.04996,"segIdx":32,"order":1},{"lat":34.2240139,"lng":109.0541478,"segIdx":32,"order":2},{"lat":34.2233992,"lng":109.0554218,"segIdx":32,"order":3},{"lat":34.2216337,"lng":109.0563485,"segIdx":32,"order":4}]},{"relationId":13040749,"key":"西安地铁|6","name":"西安地铁6号线：纺织城 → 西安南站","ref":"6","network":"西安地铁","route":"subway","color":"#485cc7","isLoop":false,"loopMode":"","loopReason":"","loopTerminalDistanceM":29156,"stations":[{"name":"纺织城","lat":34.2803158,"lng":109.0648136,"rawLat":34.2803158,"rawLng":109.0648136,"transferKey":"纺织城","platformKey":"13040749:0:纺织城","osmRefs":["node/10297659147"]},{"name":"纺二路","lat":34.271037,"lng":109.0578954,"rawLat":34.271037,"rawLng":109.0578954,"transferKey":"纺二路","platformKey":"13040749:1:纺二路","osmRefs":["node/10312280475"]},{"name":"纺六路","lat":34.2590641,"lng":109.0590127,"rawLat":34.2590641,"rawLng":109.0590127,"transferKey":"纺六路","platformKey":"13040749:2:纺六路","osmRefs":["node/10312280478"]},{"name":"穆将王","lat":34.2526703,"lng":109.0516913,"rawLat":34.2526703,"rawLng":109.0516913,"transferKey":"穆将王","platformKey":"13040749:3:穆将王","osmRefs":["node/10312280481"]},{"name":"田家湾","lat":34.252864,"lng":109.0333398,"rawLat":34.252864,"rawLng":109.0333398,"transferKey":"田家湾","platformKey":"13040749:4:田家湾","osmRefs":["node/10312280485"]},{"name":"卫星测控中心","lat":34.2526158,"lng":109.0208968,"rawLat":34.2526158,"rawLng":109.0208968,"transferKey":"卫星测控中心","platformKey":"13040749:5:卫星测控中心","osmRefs":["node/10312280487"]},{"name":"万寿南路","lat":34.2525904,"lng":109.0103445,"rawLat":34.2525904,"rawLng":109.0103445,"transferKey":"万寿南路","platformKey":"13040749:6:万寿南路","osmRefs":["node/10312280490"]},{"name":"公园南路","lat":34.2526047,"lng":109.0015611,"rawLat":34.2526047,"rawLng":109.0015611,"transferKey":"公园南路","platformKey":"13040749:7:公园南路","osmRefs":["node/10312280493"]},{"name":"咸宁路","lat":34.2526631,"lng":108.9906453,"rawLat":34.2526631,"rawLng":108.9906453,"transferKey":"咸宁路","platformKey":"13040749:8:咸宁路","osmRefs":["node/10312280495"]},{"name":"交通大学·兴庆宫","lat":34.2526611,"lng":108.9823785,"rawLat":34.2526611,"rawLng":108.9823785,"transferKey":"交通大学·兴庆宫","platformKey":"13040749:9:交通大学·兴庆宫","osmRefs":["node/10312300665"]},{"name":"长乐门","lat":34.2608502,"lng":108.9705873,"rawLat":34.2608502,"rawLng":108.9705873,"transferKey":"长乐门","platformKey":"13040749:10:长乐门","osmRefs":["node/10312300668"]},{"name":"大差市","lat":34.2611025,"lng":108.9574078,"rawLat":34.2611025,"rawLng":108.9574078,"transferKey":"大差市","platformKey":"13040749:11:大差市","osmRefs":["node/10297631896"]},{"name":"钟楼","lat":34.261191,"lng":108.9450301,"rawLat":34.261191,"rawLng":108.9450301,"transferKey":"钟楼","platformKey":"13040749:12:钟楼","osmRefs":["node/10297631895"]},{"name":"广济街","lat":34.2610671,"lng":108.9347204,"rawLat":34.2610671,"rawLng":108.9347204,"transferKey":"广济街","platformKey":"13040749:13:广济街","osmRefs":["node/10297631892"]},{"name":"桥梓口","lat":34.2610837,"lng":108.9254169,"rawLat":34.2610837,"rawLng":108.9254169,"transferKey":"桥梓口","platformKey":"13040749:14:桥梓口","osmRefs":["node/10297631891"]},{"name":"安定门","lat":34.261072,"lng":108.9177383,"rawLat":34.261072,"rawLng":108.9177383,"transferKey":"安定门","platformKey":"13040749:15:安定门","osmRefs":["node/10297631890"]},{"name":"大唐西市","lat":34.2532045,"lng":108.9053623,"rawLat":34.2532045,"rawLng":108.9053623,"transferKey":"大唐西市","platformKey":"13040749:16:大唐西市","osmRefs":["node/10312329111"]},{"name":"西北工业大学","lat":34.2424755,"lng":108.905326,"rawLat":34.2424755,"rawLng":108.905326,"transferKey":"西北工业大学","platformKey":"13040749:17:西北工业大学","osmRefs":["node/9429850166"]},{"name":"科技路","lat":34.2333689,"lng":108.9000408,"rawLat":34.2333689,"rawLng":108.9000408,"transferKey":"科技路","platformKey":"13040749:18:科技路","osmRefs":["node/9441977589"]},{"name":"甘家寨","lat":34.2252082,"lng":108.8947408,"rawLat":34.2252082,"rawLng":108.8947408,"transferKey":"甘家寨","platformKey":"13040749:19:甘家寨","osmRefs":["node/9162434839"]},{"name":"木塔寺","lat":34.2138999,"lng":108.887504,"rawLat":34.2138999,"rawLng":108.887504,"transferKey":"木塔寺","platformKey":"13040749:20:木塔寺","osmRefs":["node/9162364907"]},{"name":"省体育馆","lat":34.2047211,"lng":108.8852427,"rawLat":34.2047211,"rawLng":108.8852427,"transferKey":"省体育馆","platformKey":"13040749:21:省体育馆","osmRefs":["node/9162407830"]},{"name":"丈八一路","lat":34.1955229,"lng":108.8800003,"rawLat":34.1955229,"rawLng":108.8800003,"transferKey":"丈八一路","platformKey":"13040749:22:丈八一路","osmRefs":["node/8617662682"]},{"name":"丈八四路","lat":34.1955392,"lng":108.8660946,"rawLat":34.1955392,"rawLng":108.8660946,"transferKey":"丈八四路","platformKey":"13040749:23:丈八四路","osmRefs":["node/8968582918"]},{"name":"丈八六路","lat":34.1955337,"lng":108.8520133,"rawLat":34.1955337,"rawLng":108.8520133,"transferKey":"丈八六路","platformKey":"13040749:24:丈八六路","osmRefs":["node/9441977541"]},{"name":"造字台","lat":34.1825872,"lng":108.8418694,"rawLat":34.1825872,"rawLng":108.8418694,"transferKey":"造字台","platformKey":"13040749:25:造字台","osmRefs":["node/9441977557"]},{"name":"西部大道（西太路口）","lat":34.1721343,"lng":108.8418543,"rawLat":34.1721343,"rawLng":108.8418543,"transferKey":"西部大道西太路口","platformKey":"13040749:26:西部大道西太路口","osmRefs":["node/9441977562"]},{"name":"郭杜西","lat":34.1615684,"lng":108.8425373,"rawLat":34.1615684,"rawLng":108.8425373,"transferKey":"郭杜西","platformKey":"13040749:27:郭杜西","osmRefs":["node/9441977567"]},{"name":"仁村","lat":34.1525626,"lng":108.8405274,"rawLat":34.1525626,"rawLng":108.8405274,"transferKey":"仁村","platformKey":"13040749:28:仁村","osmRefs":["node/9441977579"]},{"name":"西安国际医学中心","lat":34.1470247,"lng":108.8340978,"rawLat":34.1470247,"rawLng":108.8340978,"transferKey":"西安国际医学中心","platformKey":"13040749:29:西安国际医学中心","osmRefs":["node/9441977585"]},{"name":"西电科大南校区·未来之瞳","lat":34.1337629,"lng":108.8257519,"rawLat":34.1337629,"rawLng":108.8257519,"transferKey":"西电科大南校区·未来之瞳","platformKey":"13040749:30:西电科大南校区·未来之瞳","osmRefs":["node/9536772488"]},{"name":"西安南站","lat":34.1228609,"lng":108.8113067,"rawLat":34.1228609,"rawLng":108.8113067,"transferKey":"西安南","platformKey":"13040749:31:西安南","osmRefs":["node/12199378117"]}],"waypoints":[{"lat":34.2803257,"lng":109.0639116,"segIdx":0,"order":0},{"lat":34.2797285,"lng":109.0597889,"segIdx":0,"order":1},{"lat":34.2777042,"lng":109.0573427,"segIdx":0,"order":2},{"lat":34.2740309,"lng":109.0569064,"segIdx":0,"order":3},{"lat":34.2716608,"lng":109.0576431,"segIdx":0,"order":4},{"lat":34.2682029,"lng":109.0590414,"segIdx":1,"order":0},{"lat":34.2625487,"lng":109.0598211,"segIdx":1,"order":1},{"lat":34.2601268,"lng":109.059248,"segIdx":1,"order":2},{"lat":34.2579485,"lng":109.0587657,"segIdx":2,"order":0},{"lat":34.2529508,"lng":109.0575664,"segIdx":2,"order":1},{"lat":34.252635,"lng":109.0549733,"segIdx":2,"order":2},{"lat":34.2526161,"lng":109.0416363,"segIdx":3,"order":0},{"lat":34.2528641,"lng":109.0342837,"segIdx":3,"order":1},{"lat":34.2528696,"lng":109.0321901,"segIdx":4,"order":0},{"lat":34.2526477,"lng":109.0304169,"segIdx":4,"order":1},{"lat":34.2525941,"lng":109.0096819,"segIdx":6,"order":0},{"lat":34.2525954,"lng":109.0035215,"segIdx":6,"order":1},{"lat":34.2526694,"lng":108.9916733,"segIdx":7,"order":0},{"lat":34.2526188,"lng":108.9877448,"segIdx":8,"order":0},{"lat":34.2526221,"lng":108.9840094,"segIdx":8,"order":1},{"lat":34.2526782,"lng":108.9816633,"segIdx":9,"order":0},{"lat":34.2536624,"lng":108.9795875,"segIdx":9,"order":1},{"lat":34.2596709,"lng":108.9764303,"segIdx":9,"order":2},{"lat":34.2605474,"lng":108.9747393,"segIdx":9,"order":3},{"lat":34.2607596,"lng":108.9722363,"segIdx":9,"order":4},{"lat":34.2610286,"lng":108.9673403,"segIdx":10,"order":0},{"lat":34.2610738,"lng":108.9585667,"segIdx":10,"order":1},{"lat":34.2611436,"lng":108.9564387,"segIdx":11,"order":0},{"lat":34.2611942,"lng":108.945857,"segIdx":11,"order":1},{"lat":34.2611867,"lng":108.9441871,"segIdx":12,"order":0},{"lat":34.261044,"lng":108.9371045,"segIdx":12,"order":1},{"lat":34.2610663,"lng":108.924058,"segIdx":14,"order":0},{"lat":34.2615542,"lng":108.92074,"segIdx":14,"order":1},{"lat":34.2611884,"lng":108.9188556,"segIdx":14,"order":2},{"lat":34.2610033,"lng":108.9153488,"segIdx":15,"order":0},{"lat":34.2597014,"lng":108.9080242,"segIdx":15,"order":1},{"lat":34.2579368,"lng":108.905907,"segIdx":15,"order":2},{"lat":34.2547208,"lng":108.9053634,"segIdx":15,"order":3},{"lat":34.24953,"lng":108.9053598,"segIdx":16,"order":0},{"lat":34.2430187,"lng":108.9053305,"segIdx":16,"order":1},{"lat":34.2413307,"lng":108.9051018,"segIdx":17,"order":0},{"lat":34.237323,"lng":108.9026557,"segIdx":17,"order":1},{"lat":34.2305306,"lng":108.8982048,"segIdx":18,"order":0},{"lat":34.2280476,"lng":108.8965756,"segIdx":18,"order":1},{"lat":34.2223544,"lng":108.892902,"segIdx":19,"order":0},{"lat":34.2148142,"lng":108.8880409,"segIdx":19,"order":1},{"lat":34.2127583,"lng":108.8867334,"segIdx":20,"order":0},{"lat":34.209345,"lng":108.8850244,"segIdx":20,"order":1},{"lat":34.2053792,"lng":108.8850602,"segIdx":20,"order":2},{"lat":34.2039974,"lng":108.8854618,"segIdx":21,"order":0},{"lat":34.1969246,"lng":108.8856426,"segIdx":21,"order":1},{"lat":34.1957732,"lng":108.8845254,"segIdx":21,"order":2},{"lat":34.1955316,"lng":108.8813585,"segIdx":21,"order":3},{"lat":34.1955313,"lng":108.875437,"segIdx":22,"order":0},{"lat":34.1955221,"lng":108.8693309,"segIdx":22,"order":1},{"lat":34.1955367,"lng":108.8588718,"segIdx":23,"order":0},{"lat":34.1955338,"lng":108.8504977,"segIdx":24,"order":0},{"lat":34.1954236,"lng":108.8451806,"segIdx":24,"order":1},{"lat":34.1939938,"lng":108.8420283,"segIdx":24,"order":2},{"lat":34.1842775,"lng":108.8418227,"segIdx":24,"order":3},{"lat":34.1809949,"lng":108.8418674,"segIdx":25,"order":0},{"lat":34.1790234,"lng":108.8418813,"segIdx":25,"order":1},{"lat":34.1659521,"lng":108.8419025,"segIdx":26,"order":0},{"lat":34.1620653,"lng":108.8424416,"segIdx":26,"order":1},{"lat":34.1600449,"lng":108.8428436,"segIdx":27,"order":0},{"lat":34.1532182,"lng":108.84084,"segIdx":27,"order":1},{"lat":34.1515681,"lng":108.8397397,"segIdx":28,"order":0},{"lat":34.1474761,"lng":108.8343707,"segIdx":28,"order":1},{"lat":34.1452361,"lng":108.8329826,"segIdx":29,"order":0},{"lat":34.136042,"lng":108.8271825,"segIdx":29,"order":1},{"lat":34.1282654,"lng":108.8223509,"segIdx":30,"order":0},{"lat":34.1216549,"lng":108.8181306,"segIdx":30,"order":1},{"lat":34.1210659,"lng":108.8160576,"segIdx":30,"order":2},{"lat":34.1215298,"lng":108.8137465,"segIdx":30,"order":3}]},{"relationId":18462995,"key":"西安地铁|8","name":"西安地铁8号线：东等驾坡→东等驾坡（内环）","ref":"8","network":"西安地铁","route":"subway","color":"#e6b10b","isLoop":false,"loopMode":"","loopReason":"","loopTerminalDistanceM":987,"stations":[{"name":"井上村","lat":34.3185908,"lng":108.9783971,"rawLat":34.3185908,"rawLng":108.9783971,"transferKey":"井上村","platformKey":"18462995:0:井上村","osmRefs":["node/12438270525"]},{"name":"北辰东路","lat":34.3185888,"lng":108.9983216,"rawLat":34.3185888,"rawLng":108.9983216,"transferKey":"北辰东路","platformKey":"18462995:1:北辰东路","osmRefs":["node/12438270593"]},{"name":"广泰门","lat":34.3133684,"lng":109.0093061,"rawLat":34.3133684,"rawLng":109.0093061,"transferKey":"广泰门","platformKey":"18462995:2:广泰门","osmRefs":["node/12438270590"]},{"name":"米家崖","lat":34.3040299,"lng":109.0102108,"rawLat":34.3040299,"rawLng":109.0102108,"transferKey":"米家崖","platformKey":"18462995:3:米家崖","osmRefs":["node/12438270588"]},{"name":"幸福林带北","lat":34.2836292,"lng":109.00929,"rawLat":34.2836292,"rawLng":109.00929,"transferKey":"幸福林带北","platformKey":"18462995:4:幸福林带北","osmRefs":["node/12438270586"]},{"name":"万寿路","lat":34.2711286,"lng":109.0092623,"rawLat":34.2711286,"rawLng":109.0092623,"transferKey":"万寿路","platformKey":"18462995:5:万寿路","osmRefs":["node/12438270584"]},{"name":"韩森寨","lat":34.2603645,"lng":109.0092426,"rawLat":34.2603645,"rawLng":109.0092426,"transferKey":"韩森寨","platformKey":"18462995:6:韩森寨","osmRefs":["node/12438270582"]},{"name":"万寿南路","lat":34.2525692,"lng":109.0092585,"rawLat":34.2525692,"rawLng":109.0092585,"transferKey":"万寿南路","platformKey":"18462995:7:万寿南路","osmRefs":["node/12438270580"]},{"name":"西等驾坡","lat":34.2426337,"lng":109.0092789,"rawLat":34.2426337,"rawLng":109.0092789,"transferKey":"西等驾坡","platformKey":"18462995:8:西等驾坡","osmRefs":["node/12438270578"]},{"name":"东等驾坡","lat":34.2302074,"lng":109.0149386,"rawLat":34.2302074,"rawLng":109.0149386,"transferKey":"东等驾坡","platformKey":"18462995:9:东等驾坡","osmRefs":["node/12438270576"]},{"name":"马腾空","lat":34.2202375,"lng":109.023327,"rawLat":34.2202375,"rawLng":109.023327,"transferKey":"马腾空","platformKey":"18462995:10:马腾空","osmRefs":["node/12438270574"]},{"name":"植物园","lat":34.2116805,"lng":109.0201161,"rawLat":34.2116805,"rawLng":109.0201161,"transferKey":"植物园","platformKey":"18462995:11:植物园","osmRefs":["node/12438270572"]},{"name":"缪家寨","lat":34.2092333,"lng":109.0084996,"rawLat":34.2092333,"rawLng":109.0084996,"transferKey":"缪家寨","platformKey":"18462995:12:缪家寨","osmRefs":["node/12438270570"]},{"name":"新开门","lat":34.2015323,"lng":108.9935528,"rawLat":34.2015323,"rawLng":108.9935528,"transferKey":"新开门","platformKey":"18462995:13:新开门","osmRefs":["node/12438270568"]},{"name":"寒窑","lat":34.2016009,"lng":108.983774,"rawLat":34.2016009,"rawLng":108.983774,"transferKey":"寒窑","platformKey":"18462995:14:寒窑","osmRefs":["node/12438270566"]},{"name":"曲江池西","lat":34.1990483,"lng":108.9711365,"rawLat":34.1990483,"rawLng":108.9711365,"transferKey":"曲江池西","platformKey":"18462995:15:曲江池西","osmRefs":["node/12438270564"]},{"name":"大唐不夜城","lat":34.1984662,"lng":108.9592933,"rawLat":34.1984662,"rawLng":108.9592933,"transferKey":"大唐不夜城","platformKey":"18462995:16:大唐不夜城","osmRefs":["node/12438270562"]},{"name":"电视塔","lat":34.1997449,"lng":108.9412296,"rawLat":34.1997449,"rawLng":108.9412296,"transferKey":"电视塔","platformKey":"18462995:17:电视塔","osmRefs":["node/12438270560"]},{"name":"东仪路","lat":34.2001704,"lng":108.923624,"rawLat":34.2001704,"rawLng":108.923624,"transferKey":"东仪路","platformKey":"18462995:18:东仪路","osmRefs":["node/9370555389"]},{"name":"安化门","lat":34.200093,"lng":108.9149462,"rawLat":34.200093,"rawLng":108.9149462,"transferKey":"安化门","platformKey":"18462995:19:安化门","osmRefs":["node/9370555335"]},{"name":"山门口","lat":34.1998821,"lng":108.9002682,"rawLat":34.1998821,"rawLng":108.9002682,"transferKey":"山门口","platformKey":"18462995:20:山门口","osmRefs":["node/8617662680"]},{"name":"省体育馆","lat":34.2047542,"lng":108.8853923,"rawLat":34.2047542,"rawLng":108.8853923,"transferKey":"省体育馆","platformKey":"18462995:21:省体育馆","osmRefs":["node/9536838736"]},{"name":"木塔寺西","lat":34.2140711,"lng":108.8851267,"rawLat":34.2140711,"rawLng":108.8851267,"transferKey":"木塔寺西","platformKey":"18462995:22:木塔寺西","osmRefs":["node/12438270555"]},{"name":"科技二路","lat":34.227268,"lng":108.885022,"rawLat":34.227268,"rawLng":108.885022,"transferKey":"科技二路","platformKey":"18462995:23:科技二路","osmRefs":["node/12438270553"]},{"name":"延平门","lat":34.2373743,"lng":108.8835272,"rawLat":34.2373743,"rawLng":108.8835272,"transferKey":"延平门","platformKey":"18462995:24:延平门","osmRefs":["node/12438270551"]},{"name":"金光门","lat":34.2530077,"lng":108.884842,"rawLat":34.2530077,"rawLng":108.884842,"transferKey":"金光门","platformKey":"18462995:25:金光门","osmRefs":["node/9391406582"]},{"name":"土门","lat":34.2610177,"lng":108.8848696,"rawLat":34.2610177,"rawLng":108.8848696,"transferKey":"土门","platformKey":"18462995:26:土门","osmRefs":["node/12438270548"]},{"name":"开远门","lat":34.2727058,"lng":108.8869462,"rawLat":34.2727058,"rawLng":108.8869462,"transferKey":"开远门","platformKey":"18462995:27:开远门","osmRefs":["node/12438270545"]},{"name":"白家口","lat":34.2835307,"lng":108.8868196,"rawLat":34.2835307,"rawLng":108.8868196,"transferKey":"白家口","platformKey":"18462995:28:白家口","osmRefs":["node/12438270543"]},{"name":"光化门","lat":34.2879849,"lng":108.8978598,"rawLat":34.2879849,"rawLng":108.8978598,"transferKey":"光化门","platformKey":"18462995:29:光化门","osmRefs":["node/12438270542"]},{"name":"景曜门","lat":34.2863914,"lng":108.9085432,"rawLat":34.2863914,"rawLng":108.9085432,"transferKey":"景曜门","platformKey":"18462995:30:景曜门","osmRefs":["node/12438270540"]},{"name":"红庙坡","lat":34.2917883,"lng":108.9177256,"rawLat":34.2917883,"rawLng":108.9177256,"transferKey":"红庙坡","platformKey":"18462995:31:红庙坡","osmRefs":["node/12438270538"]},{"name":"大风阁","lat":34.3036749,"lng":108.9185958,"rawLat":34.3036749,"rawLng":108.9185958,"transferKey":"大风阁","platformKey":"18462995:32:大风阁","osmRefs":["node/12438270535"]},{"name":"霸城门","lat":34.3193924,"lng":108.9251216,"rawLat":34.3193924,"rawLng":108.9251216,"transferKey":"霸城门","platformKey":"18462995:33:霸城门","osmRefs":["node/12438270534"]},{"name":"青少年中心","lat":34.3193658,"lng":108.9417254,"rawLat":34.3193658,"rawLng":108.9417254,"transferKey":"青少年中心","platformKey":"18462995:34:青少年中心","osmRefs":["node/12438270532"]},{"name":"市第三医院","lat":34.3194057,"lng":108.9556169,"rawLat":34.3194057,"rawLng":108.9556169,"transferKey":"市第三医院","platformKey":"18462995:35:市第三医院","osmRefs":["node/12438270530"]},{"name":"余家寨","lat":34.3187522,"lng":108.9676512,"rawLat":34.3187522,"rawLng":108.9676512,"transferKey":"余家寨","platformKey":"18462995:36:余家寨","osmRefs":["node/12438270527"]}],"waypoints":[{"lat":34.3185808,"lng":108.9797928,"segIdx":0,"order":0},{"lat":34.3185879,"lng":108.997228,"segIdx":0,"order":1},{"lat":34.3185899,"lng":108.9996597,"segIdx":1,"order":0},{"lat":34.3183594,"lng":109.0074065,"segIdx":1,"order":1},{"lat":34.3174117,"lng":109.0086949,"segIdx":1,"order":2},{"lat":34.3158308,"lng":109.00927,"segIdx":1,"order":3},{"lat":34.3126947,"lng":109.0093183,"segIdx":2,"order":0},{"lat":34.3117793,"lng":109.0094341,"segIdx":2,"order":1},{"lat":34.3030196,"lng":109.0103146,"segIdx":3,"order":0},{"lat":34.2859691,"lng":109.0092987,"segIdx":3,"order":1},{"lat":34.270552,"lng":109.0092622,"segIdx":5,"order":0},{"lat":34.2609305,"lng":109.0092414,"segIdx":5,"order":1},{"lat":34.2374396,"lng":109.0092895,"segIdx":8,"order":0},{"lat":34.2352257,"lng":109.0098904,"segIdx":8,"order":1},{"lat":34.2320325,"lng":109.0134008,"segIdx":8,"order":2},{"lat":34.229744,"lng":109.0153381,"segIdx":9,"order":0},{"lat":34.2211365,"lng":109.0225659,"segIdx":9,"order":1},{"lat":34.218907,"lng":109.0244114,"segIdx":10,"order":0},{"lat":34.2175026,"lng":109.0251297,"segIdx":10,"order":1},{"lat":34.2156106,"lng":109.0248045,"segIdx":10,"order":2},{"lat":34.2119337,"lng":109.0207071,"segIdx":10,"order":3},{"lat":34.211199,"lng":109.0189192,"segIdx":11,"order":0},{"lat":34.2094723,"lng":109.0096723,"segIdx":11,"order":1},{"lat":34.2090368,"lng":109.0075064,"segIdx":12,"order":0},{"lat":34.208261,"lng":109.0023561,"segIdx":12,"order":1},{"lat":34.2022235,"lng":108.9982995,"segIdx":12,"order":2},{"lat":34.2015362,"lng":108.9946303,"segIdx":12,"order":3},{"lat":34.2015291,"lng":108.9926905,"segIdx":13,"order":0},{"lat":34.2016148,"lng":108.9861477,"segIdx":13,"order":1},{"lat":34.2016013,"lng":108.9831593,"segIdx":14,"order":0},{"lat":34.1993271,"lng":108.9776263,"segIdx":14,"order":1},{"lat":34.1990583,"lng":108.9717541,"segIdx":14,"order":2},{"lat":34.1990399,"lng":108.970452,"segIdx":15,"order":0},{"lat":34.1985385,"lng":108.9614241,"segIdx":15,"order":1},{"lat":34.1984684,"lng":108.9573637,"segIdx":16,"order":0},{"lat":34.1994568,"lng":108.9520477,"segIdx":16,"order":1},{"lat":34.1997434,"lng":108.9422002,"segIdx":16,"order":2},{"lat":34.1997389,"lng":108.9401802,"segIdx":17,"order":0},{"lat":34.2001758,"lng":108.9264646,"segIdx":17,"order":1},{"lat":34.2001866,"lng":108.922055,"segIdx":18,"order":0},{"lat":34.2001273,"lng":108.9171683,"segIdx":18,"order":1},{"lat":34.2000452,"lng":108.906411,"segIdx":19,"order":0},{"lat":34.1998943,"lng":108.9020809,"segIdx":19,"order":1},{"lat":34.1998713,"lng":108.8989844,"segIdx":20,"order":0},{"lat":34.2002326,"lng":108.8868688,"segIdx":20,"order":1},{"lat":34.2011028,"lng":108.885838,"segIdx":20,"order":2},{"lat":34.2040548,"lng":108.8855701,"segIdx":20,"order":3},{"lat":34.2053758,"lng":108.8852124,"segIdx":21,"order":0},{"lat":34.2125364,"lng":108.8851243,"segIdx":21,"order":1},{"lat":34.2150048,"lng":108.8851229,"segIdx":22,"order":0},{"lat":34.2251489,"lng":108.8850469,"segIdx":22,"order":1},{"lat":34.2280591,"lng":108.8850162,"segIdx":23,"order":0},{"lat":34.2330675,"lng":108.8849399,"segIdx":23,"order":1},{"lat":34.2366329,"lng":108.8835256,"segIdx":23,"order":2},{"lat":34.2387489,"lng":108.8835319,"segIdx":24,"order":0},{"lat":34.2487875,"lng":108.8848712,"segIdx":24,"order":1},{"lat":34.2543001,"lng":108.8848392,"segIdx":25,"order":0},{"lat":34.2602743,"lng":108.8848765,"segIdx":25,"order":1},{"lat":34.2622152,"lng":108.8848586,"segIdx":26,"order":0},{"lat":34.2666408,"lng":108.8851817,"segIdx":26,"order":1},{"lat":34.2717804,"lng":108.8869558,"segIdx":26,"order":2},{"lat":34.274154,"lng":108.8869312,"segIdx":27,"order":0},{"lat":34.2797292,"lng":108.8862898,"segIdx":27,"order":1},{"lat":34.282312,"lng":108.8868384,"segIdx":27,"order":2},{"lat":34.2847047,"lng":108.8867884,"segIdx":28,"order":0},{"lat":34.2868184,"lng":108.8872607,"segIdx":28,"order":1},{"lat":34.2878682,"lng":108.8888523,"segIdx":28,"order":2},{"lat":34.2879488,"lng":108.8956484,"segIdx":28,"order":3},{"lat":34.2879929,"lng":108.8993842,"segIdx":29,"order":0},{"lat":34.2866139,"lng":108.9038457,"segIdx":29,"order":1},{"lat":34.2864073,"lng":108.9073001,"segIdx":29,"order":2},{"lat":34.2863734,"lng":108.9099552,"segIdx":30,"order":0},{"lat":34.2867417,"lng":108.9168702,"segIdx":30,"order":1},{"lat":34.2879633,"lng":108.9176355,"segIdx":30,"order":2},{"lat":34.2910427,"lng":108.9177239,"segIdx":30,"order":3},{"lat":34.2926772,"lng":108.9177358,"segIdx":31,"order":0},{"lat":34.3019786,"lng":108.9184072,"segIdx":31,"order":1},{"lat":34.3045488,"lng":108.918693,"segIdx":32,"order":0},{"lat":34.3180568,"lng":108.9181164,"segIdx":32,"order":1},{"lat":34.3191295,"lng":108.919402,"segIdx":32,"order":2},{"lat":34.319398,"lng":108.9241974,"segIdx":32,"order":3},{"lat":34.3193759,"lng":108.9278487,"segIdx":33,"order":0},{"lat":34.3193647,"lng":108.9405822,"segIdx":33,"order":1},{"lat":34.3193678,"lng":108.9438277,"segIdx":34,"order":0},{"lat":34.3193942,"lng":108.9538278,"segIdx":34,"order":1},{"lat":34.319411,"lng":108.9567597,"segIdx":35,"order":0},{"lat":34.3187583,"lng":108.9665685,"segIdx":35,"order":1}]},{"relationId":10608559,"key":"西安地铁|9","name":"西安地铁9号线：秦陵西 → 纺织城","ref":"9","network":"西安地铁","route":"subway","color":"#ff9e1b","isLoop":false,"loopMode":"","loopReason":"","loopTerminalDistanceM":20071,"stations":[{"name":"秦陵西","lat":34.3974391,"lng":109.2312873,"rawLat":34.3974391,"rawLng":109.2312873,"transferKey":"秦陵西","platformKey":"10608559:0:秦陵西","osmRefs":["node/9555755373"]},{"name":"银桥大道","lat":34.3884451,"lng":109.2231972,"rawLat":34.3884451,"rawLng":109.2231972,"transferKey":"银桥大道","platformKey":"10608559:1:银桥大道","osmRefs":["node/9555755398"]},{"name":"东三岔","lat":34.3782916,"lng":109.2164172,"rawLat":34.3782916,"rawLng":109.2164172,"transferKey":"东三岔","platformKey":"10608559:2:东三岔","osmRefs":["node/9555755409"]},{"name":"华清池","lat":34.3678455,"lng":109.2076051,"rawLat":34.3678455,"rawLng":109.2076051,"transferKey":"华清池","platformKey":"10608559:3:华清池","osmRefs":["node/8971324350"]},{"name":"西花园","lat":34.371821,"lng":109.1957802,"rawLat":34.371821,"rawLng":109.1957802,"transferKey":"西花园","platformKey":"10608559:4:西花园","osmRefs":["node/8971294694"]},{"name":"西工程大·西科大（临潼校区）","lat":34.3716793,"lng":109.1840496,"rawLat":34.3716793,"rawLng":109.1840496,"transferKey":"西工程大·西科大临潼校区","platformKey":"10608559:5:西工程大·西科大临潼校区","osmRefs":["node/8971370510"]},{"name":"芷阳广场","lat":34.3666837,"lng":109.1732678,"rawLat":34.3666837,"rawLng":109.1732678,"transferKey":"芷阳广场","platformKey":"10608559:6:芷阳广场","osmRefs":["node/9556123919"]},{"name":"鹦鹉寺公园","lat":34.3560577,"lng":109.1615035,"rawLat":34.3560577,"rawLng":109.1615035,"transferKey":"鹦鹉寺公园","platformKey":"10608559:7:鹦鹉寺公园","osmRefs":["node/8971324338"]},{"name":"凤凰池","lat":34.3455206,"lng":109.1443954,"rawLat":34.3455206,"rawLng":109.1443954,"transferKey":"凤凰池","platformKey":"10608559:8:凤凰池","osmRefs":["node/9556118095"]},{"name":"紫霞三路","lat":34.3352619,"lng":109.1268109,"rawLat":34.3352619,"rawLng":109.1268109,"transferKey":"紫霞三路","platformKey":"10608559:9:紫霞三路","osmRefs":["node/9556118109"]},{"name":"洪庆","lat":34.3180484,"lng":109.1125001,"rawLat":34.3180484,"rawLng":109.1125001,"transferKey":"洪庆","platformKey":"10608559:10:洪庆","osmRefs":["node/9556159724"]},{"name":"田王","lat":34.2979512,"lng":109.1125159,"rawLat":34.2979512,"rawLng":109.1125159,"transferKey":"田王","platformKey":"10608559:11:田王","osmRefs":["node/8971294670"]},{"name":"灞柳二路","lat":34.2820384,"lng":109.1098847,"rawLat":34.2820384,"rawLng":109.1098847,"transferKey":"灞柳二路","platformKey":"10608559:12:灞柳二路","osmRefs":["node/8971294707"]},{"name":"香王","lat":34.2765789,"lng":109.0919102,"rawLat":34.2765789,"rawLng":109.0919102,"transferKey":"香王","platformKey":"10608559:13:香王","osmRefs":["node/9327269567"]},{"name":"纺织城","lat":34.2804453,"lng":109.0648155,"rawLat":34.2804453,"rawLng":109.0648155,"transferKey":"纺织城","platformKey":"10608559:14:纺织城","osmRefs":["node/9221463287"]}],"waypoints":[{"lat":34.3969708,"lng":109.2309211,"segIdx":0,"order":0},{"lat":34.3899164,"lng":109.2246258,"segIdx":0,"order":1},{"lat":34.3867279,"lng":109.2216468,"segIdx":1,"order":0},{"lat":34.3799627,"lng":109.2173008,"segIdx":1,"order":1},{"lat":34.3776205,"lng":109.2160315,"segIdx":2,"order":0},{"lat":34.3744665,"lng":109.213576,"segIdx":2,"order":1},{"lat":34.3684967,"lng":109.2120808,"segIdx":2,"order":2},{"lat":34.3676699,"lng":109.210284,"segIdx":2,"order":3},{"lat":34.3679287,"lng":109.2061365,"segIdx":3,"order":0},{"lat":34.368292,"lng":109.2018205,"segIdx":3,"order":1},{"lat":34.3709669,"lng":109.1972058,"segIdx":3,"order":2},{"lat":34.372395,"lng":109.1948231,"segIdx":4,"order":0},{"lat":34.3731367,"lng":109.1911646,"segIdx":4,"order":1},{"lat":34.3718151,"lng":109.184746,"segIdx":4,"order":2},{"lat":34.3713255,"lng":109.1821756,"segIdx":5,"order":0},{"lat":34.370437,"lng":109.1779623,"segIdx":5,"order":1},{"lat":34.3670902,"lng":109.1738589,"segIdx":5,"order":2},{"lat":34.366209,"lng":109.1726177,"segIdx":6,"order":0},{"lat":34.356937,"lng":109.1624935,"segIdx":6,"order":1},{"lat":34.3547121,"lng":109.1600267,"segIdx":7,"order":0},{"lat":34.3467545,"lng":109.1466171,"segIdx":7,"order":1},{"lat":34.3448565,"lng":109.1431215,"segIdx":8,"order":0},{"lat":34.3358928,"lng":109.1276892,"segIdx":8,"order":1},{"lat":34.3348334,"lng":109.1262601,"segIdx":9,"order":0},{"lat":34.3263375,"lng":109.1154864,"segIdx":9,"order":1},{"lat":34.3225082,"lng":109.1128283,"segIdx":9,"order":2},{"lat":34.3200953,"lng":109.1124875,"segIdx":9,"order":3},{"lat":34.3157234,"lng":109.1125262,"segIdx":10,"order":0},{"lat":34.299093,"lng":109.1125078,"segIdx":10,"order":1},{"lat":34.2954075,"lng":109.1124938,"segIdx":11,"order":0},{"lat":34.285287,"lng":109.1120383,"segIdx":11,"order":1},{"lat":34.2831635,"lng":109.1111521,"segIdx":11,"order":2},{"lat":34.2807953,"lng":109.1084924,"segIdx":12,"order":0},{"lat":34.2745073,"lng":109.1006137,"segIdx":12,"order":1},{"lat":34.2746188,"lng":109.0978581,"segIdx":12,"order":2},{"lat":34.2760826,"lng":109.0934504,"segIdx":12,"order":3},{"lat":34.2769572,"lng":109.090853,"segIdx":13,"order":0},{"lat":34.2804337,"lng":109.0656778,"segIdx":13,"order":1}]},{"relationId":18089013,"key":"西安地铁|10","name":"西安地铁10号线：井上村→昭慧广场","ref":"10","network":"西安地铁","route":"subway","color":"#009f4d","isLoop":false,"loopMode":"","loopReason":"","loopTerminalDistanceM":25513,"stations":[{"name":"井上村","lat":34.318632,"lng":108.9794157,"rawLat":34.318632,"rawLng":108.9794157,"transferKey":"井上村","platformKey":"18089013:0:井上村","osmRefs":["node/12199280338"]},{"name":"帽珥冢","lat":34.3311955,"lng":108.9794465,"rawLat":34.3311955,"rawLng":108.9794465,"transferKey":"帽珥冢","platformKey":"18089013:1:帽珥冢","osmRefs":["node/12199280335"]},{"name":"团结村","lat":34.3415186,"lng":108.9795315,"rawLat":34.3415186,"rawLng":108.9795315,"transferKey":"团结村","platformKey":"18089013:2:团结村","osmRefs":["node/12199280332"]},{"name":"红旗厂","lat":34.3553955,"lng":108.9769095,"rawLat":34.3553955,"rawLng":108.9769095,"transferKey":"红旗厂","platformKey":"18089013:3:红旗厂","osmRefs":["node/12199280329"]},{"name":"西安工大·武德路","lat":34.3751782,"lng":108.9769013,"rawLat":34.3751782,"rawLng":108.9769013,"transferKey":"西安工大·武德路","platformKey":"18089013:4:西安工大·武德路","osmRefs":["node/12199280323"]},{"name":"景家堡","lat":34.3934848,"lng":108.977686,"rawLat":34.3934848,"rawLng":108.977686,"transferKey":"景家堡","platformKey":"18089013:5:景家堡","osmRefs":["node/12199280320"]},{"name":"未央湖","lat":34.4087126,"lng":108.987703,"rawLat":34.4087126,"rawLng":108.987703,"transferKey":"未央湖","platformKey":"18089013:6:未央湖","osmRefs":["node/12199280317"]},{"name":"西堡","lat":34.4121248,"lng":109.0219731,"rawLat":34.4121248,"rawLng":109.0219731,"transferKey":"西堡","platformKey":"18089013:7:西堡","osmRefs":["node/11869850819"]},{"name":"水流","lat":34.4284416,"lng":109.0345277,"rawLat":34.4284416,"rawLng":109.0345277,"transferKey":"水流","platformKey":"18089013:8:水流","osmRefs":["node/11869850820"]},{"name":"泾渭半岛","lat":34.4518617,"lng":109.0331271,"rawLat":34.4518617,"rawLng":109.0331271,"transferKey":"泾渭半岛","platformKey":"18089013:9:泾渭半岛","osmRefs":["node/11869850823"]},{"name":"杨官寨","lat":34.4690921,"lng":109.0310644,"rawLat":34.4690921,"rawLng":109.0310644,"transferKey":"杨官寨","platformKey":"18089013:10:杨官寨","osmRefs":["node/11869850824"]},{"name":"军庄","lat":34.4902436,"lng":109.0295385,"rawLat":34.4902436,"rawLng":109.0295385,"transferKey":"军庄","platformKey":"18089013:11:军庄","osmRefs":["node/11869850827"]},{"name":"崇皇","lat":34.5057779,"lng":109.0337377,"rawLat":34.5057779,"rawLng":109.0337377,"transferKey":"崇皇","platformKey":"18089013:12:崇皇","osmRefs":["node/11869850829"]},{"name":"榆楚","lat":34.5073626,"lng":109.0568814,"rawLat":34.5073626,"rawLng":109.0568814,"transferKey":"榆楚","platformKey":"18089013:13:榆楚","osmRefs":["node/11869850832"]},{"name":"鹿苑大道","lat":34.5088082,"lng":109.0771482,"rawLat":34.5088082,"rawLng":109.0771482,"transferKey":"鹿苑大道","platformKey":"18089013:14:鹿苑大道","osmRefs":["node/11400994280"]},{"name":"杏王","lat":34.5106279,"lng":109.0985811,"rawLat":34.5106279,"rawLng":109.0985811,"transferKey":"杏王","platformKey":"18089013:15:杏王","osmRefs":["node/11400994299"]},{"name":"昭慧广场","lat":34.523324,"lng":109.105078,"rawLat":34.523324,"rawLng":109.105078,"transferKey":"昭慧广场","platformKey":"18089013:16:昭慧广场","osmRefs":["node/11869850836"]}],"waypoints":[{"lat":34.3218514,"lng":108.9793609,"segIdx":0,"order":0},{"lat":34.3302867,"lng":108.9794354,"segIdx":0,"order":1},{"lat":34.3320541,"lng":108.979457,"segIdx":1,"order":0},{"lat":34.3409768,"lng":108.9795333,"segIdx":1,"order":1},{"lat":34.342211,"lng":108.9795298,"segIdx":2,"order":0},{"lat":34.3498517,"lng":108.9794697,"segIdx":2,"order":1},{"lat":34.352215,"lng":108.9772188,"segIdx":2,"order":2},{"lat":34.3534468,"lng":108.976913,"segIdx":2,"order":3},{"lat":34.3644076,"lng":108.976893,"segIdx":3,"order":0},{"lat":34.3673497,"lng":108.9774067,"segIdx":3,"order":1},{"lat":34.3744547,"lng":108.9768838,"segIdx":3,"order":2},{"lat":34.3761656,"lng":108.9769251,"segIdx":4,"order":0},{"lat":34.3863643,"lng":108.9772249,"segIdx":4,"order":1},{"lat":34.3898204,"lng":108.9784802,"segIdx":4,"order":2},{"lat":34.3923315,"lng":108.9779233,"segIdx":4,"order":3},{"lat":34.3942296,"lng":108.9775327,"segIdx":5,"order":0},{"lat":34.4028263,"lng":108.9764199,"segIdx":5,"order":1},{"lat":34.4057044,"lng":108.9771711,"segIdx":5,"order":2},{"lat":34.4074182,"lng":108.9798016,"segIdx":5,"order":3},{"lat":34.4085487,"lng":108.9866596,"segIdx":5,"order":4},{"lat":34.4088335,"lng":108.9884436,"segIdx":6,"order":0},{"lat":34.4114637,"lng":109.0045222,"segIdx":6,"order":1},{"lat":34.4121306,"lng":109.021306,"segIdx":6,"order":2},{"lat":34.4121165,"lng":109.0229325,"segIdx":7,"order":0},{"lat":34.4124319,"lng":109.0304975,"segIdx":7,"order":1},{"lat":34.4147392,"lng":109.0341532,"segIdx":7,"order":2},{"lat":34.4173024,"lng":109.0351167,"segIdx":7,"order":3},{"lat":34.4275391,"lng":109.0345732,"segIdx":7,"order":4},{"lat":34.4294523,"lng":109.0344767,"segIdx":8,"order":0},{"lat":34.4329837,"lng":109.0347373,"segIdx":8,"order":1},{"lat":34.4497516,"lng":109.033307,"segIdx":8,"order":2},{"lat":34.4524442,"lng":109.0330776,"segIdx":9,"order":0},{"lat":34.4680715,"lng":109.0311461,"segIdx":9,"order":1},{"lat":34.4707068,"lng":109.0309352,"segIdx":10,"order":0},{"lat":34.489264,"lng":109.0296159,"segIdx":10,"order":1},{"lat":34.491279,"lng":109.0294567,"segIdx":11,"order":0},{"lat":34.5027879,"lng":109.0287119,"segIdx":11,"order":1},{"lat":34.505062,"lng":109.0305122,"segIdx":11,"order":2},{"lat":34.5057286,"lng":109.0331128,"segIdx":11,"order":3},{"lat":34.505909,"lng":109.0357178,"segIdx":12,"order":0},{"lat":34.507326,"lng":109.0556815,"segIdx":12,"order":1},{"lat":34.5075247,"lng":109.0583877,"segIdx":13,"order":0},{"lat":34.5087699,"lng":109.0763686,"segIdx":13,"order":1},{"lat":34.5089691,"lng":109.0783931,"segIdx":14,"order":0},{"lat":34.5105955,"lng":109.0977293,"segIdx":14,"order":1},{"lat":34.5106927,"lng":109.0993967,"segIdx":15,"order":0},{"lat":34.5115615,"lng":109.1027762,"segIdx":15,"order":1},{"lat":34.5137081,"lng":109.104709,"segIdx":15,"order":2},{"lat":34.522673,"lng":109.1050697,"segIdx":15,"order":3}]},{"relationId":10381386,"key":"西安地铁|14","name":"西安地铁14号线：贺韶→机场西（T1、T2、T3）","ref":"14","network":"西安地铁","route":"subway","color":"#00c1d5","isLoop":false,"loopMode":"","loopReason":"","loopTerminalDistanceM":30038,"stations":[{"name":"贺韶","lat":34.3677807,"lng":109.0725905,"rawLat":34.3677807,"rawLng":109.0725905,"transferKey":"贺韶","platformKey":"10381386:0:贺韶","osmRefs":["node/9533747495"]},{"name":"港务大道","lat":34.3690854,"lng":109.062089,"rawLat":34.3690854,"rawLng":109.062089,"transferKey":"港务大道","platformKey":"10381386:1:港务大道","osmRefs":["node/9533747512"]},{"name":"新寺","lat":34.3710474,"lng":109.0486619,"rawLat":34.3710474,"rawLng":109.0486619,"transferKey":"新寺","platformKey":"10381386:2:新寺","osmRefs":["node/9533916689"]},{"name":"双寨","lat":34.3725785,"lng":109.0358476,"rawLat":34.3725785,"rawLng":109.0358476,"transferKey":"双寨","platformKey":"10381386:3:双寨","osmRefs":["node/9335653681"]},{"name":"奥体中心","lat":34.3748259,"lng":109.0162297,"rawLat":34.3748259,"rawLng":109.0162297,"transferKey":"奥体中心","platformKey":"10381386:4:奥体中心","osmRefs":["node/9536195302"]},{"name":"北辰","lat":34.3730633,"lng":108.9909548,"rawLat":34.3730633,"rawLng":108.9909548,"transferKey":"北辰","platformKey":"10381386:5:北辰","osmRefs":["node/9536195314"]},{"name":"西安工大·武德路","lat":34.3750764,"lng":108.9778664,"rawLat":34.3750764,"rawLng":108.9778664,"transferKey":"西安工大·武德路","platformKey":"10381386:6:西安工大·武德路","osmRefs":["node/9536285321"]},{"name":"文景山公园","lat":34.3825574,"lng":108.9459688,"rawLat":34.3825574,"rawLng":108.9459688,"transferKey":"文景山公园","platformKey":"10381386:7:文景山公园","osmRefs":["node/9536287598"]},{"name":"西安北站","lat":34.3811412,"lng":108.9340905,"rawLat":34.3811412,"rawLng":108.9340905,"transferKey":"西安北","platformKey":"10381386:8:西安北","osmRefs":["node/9452865076"]},{"name":"渭河南","lat":34.3940982,"lng":108.918469,"rawLat":34.3940982,"rawLng":108.918469,"transferKey":"渭河南","platformKey":"10381386:9:渭河南","osmRefs":["node/9452865057"]},{"name":"秦宫","lat":34.4071562,"lng":108.8668197,"rawLat":34.4071562,"rawLng":108.8668197,"transferKey":"秦宫","platformKey":"10381386:10:秦宫","osmRefs":["node/7039495523"]},{"name":"秦汉新城","lat":34.3996769,"lng":108.843632,"rawLat":34.3996769,"rawLng":108.843632,"transferKey":"秦汉新城","platformKey":"10381386:11:秦汉新城","osmRefs":["node/7039495518"]},{"name":"长陵","lat":34.3914025,"lng":108.8244312,"rawLat":34.3914025,"rawLng":108.8244312,"transferKey":"长陵","platformKey":"10381386:12:长陵","osmRefs":["node/7039495515"]},{"name":"摆旗寨","lat":34.3915504,"lng":108.7920328,"rawLat":34.3915504,"rawLng":108.7920328,"transferKey":"摆旗寨","platformKey":"10381386:13:摆旗寨","osmRefs":["node/7039495513"]},{"name":"艺术中心","lat":34.4206144,"lng":108.7950943,"rawLat":34.4206144,"rawLng":108.7950943,"transferKey":"艺术中心","platformKey":"10381386:14:艺术中心","osmRefs":["node/5761862465"]},{"name":"空港新城","lat":34.4306403,"lng":108.7938913,"rawLat":34.4306403,"rawLng":108.7938913,"transferKey":"空港新城","platformKey":"10381386:15:空港新城","osmRefs":["node/7039495508"]},{"name":"机场（T5）","lat":34.4557244,"lng":108.7799909,"rawLat":34.4557244,"rawLng":108.7799909,"transferKey":"机场t5","platformKey":"10381386:16:机场t5","osmRefs":["node/12598093092"]},{"name":"机场西（T1、T2、T3）","lat":34.4403076,"lng":108.7572049,"rawLat":34.4403076,"rawLng":108.7572049,"transferKey":"机场西t1、t2、t3","platformKey":"10381386:17:机场西t1、t2、t3","osmRefs":["node/9536461575"]}],"waypoints":[{"lat":34.3679187,"lng":109.0716348,"segIdx":0,"order":0},{"lat":34.3690138,"lng":109.0626919,"segIdx":0,"order":1},{"lat":34.3701251,"lng":109.0548551,"segIdx":1,"order":0},{"lat":34.3704014,"lng":109.0529995,"segIdx":1,"order":1},{"lat":34.371502,"lng":109.0454978,"segIdx":2,"order":0},{"lat":34.3725094,"lng":109.0365138,"segIdx":2,"order":1},{"lat":34.3730806,"lng":109.0310769,"segIdx":3,"order":0},{"lat":34.3745649,"lng":109.0179981,"segIdx":3,"order":1},{"lat":34.3750789,"lng":109.0143064,"segIdx":4,"order":0},{"lat":34.3747161,"lng":109.0120607,"segIdx":4,"order":1},{"lat":34.3708933,"lng":109.0062712,"segIdx":4,"order":2},{"lat":34.3727783,"lng":108.9927691,"segIdx":4,"order":3},{"lat":34.3740649,"lng":108.984378,"segIdx":5,"order":0},{"lat":34.374918,"lng":108.9788638,"segIdx":5,"order":1},{"lat":34.3754371,"lng":108.9755556,"segIdx":6,"order":0},{"lat":34.3772561,"lng":108.9674212,"segIdx":6,"order":1},{"lat":34.3783853,"lng":108.9651534,"segIdx":6,"order":2},{"lat":34.3851076,"lng":108.9597136,"segIdx":6,"order":3},{"lat":34.3852364,"lng":108.9577543,"segIdx":6,"order":4},{"lat":34.3828754,"lng":108.9475039,"segIdx":6,"order":5},{"lat":34.3822185,"lng":108.9444017,"segIdx":7,"order":0},{"lat":34.3813597,"lng":108.9349295,"segIdx":7,"order":1},{"lat":34.3809518,"lng":108.9333453,"segIdx":8,"order":0},{"lat":34.379527,"lng":108.9267002,"segIdx":8,"order":1},{"lat":34.3806298,"lng":108.9237071,"segIdx":8,"order":2},{"lat":34.3928532,"lng":108.9188954,"segIdx":8,"order":3},{"lat":34.3946456,"lng":108.9182633,"segIdx":9,"order":0},{"lat":34.4114648,"lng":108.9133635,"segIdx":9,"order":1},{"lat":34.4139385,"lng":108.9102717,"segIdx":9,"order":2},{"lat":34.415835,"lng":108.9035163,"segIdx":9,"order":3},{"lat":34.4164379,"lng":108.9003672,"segIdx":9,"order":4},{"lat":34.4162202,"lng":108.8975397,"segIdx":9,"order":5},{"lat":34.4074117,"lng":108.8676167,"segIdx":9,"order":6},{"lat":34.4069204,"lng":108.8660921,"segIdx":10,"order":0},{"lat":34.4001592,"lng":108.8450958,"segIdx":10,"order":1},{"lat":34.3993838,"lng":108.8427288,"segIdx":11,"order":0},{"lat":34.396153,"lng":108.8337341,"segIdx":11,"order":1},{"lat":34.391902,"lng":108.8255085,"segIdx":11,"order":2},{"lat":34.3910713,"lng":108.8237349,"segIdx":12,"order":0},{"lat":34.383783,"lng":108.8062787,"segIdx":12,"order":1},{"lat":34.3830765,"lng":108.8020402,"segIdx":12,"order":2},{"lat":34.3835593,"lng":108.7989443,"segIdx":12,"order":3},{"lat":34.3852998,"lng":108.7955601,"segIdx":12,"order":4},{"lat":34.3871856,"lng":108.7937665,"segIdx":12,"order":5},{"lat":34.3908532,"lng":108.7922307,"segIdx":12,"order":6},{"lat":34.3923889,"lng":108.7917243,"segIdx":13,"order":0},{"lat":34.4066842,"lng":108.7873733,"segIdx":13,"order":1},{"lat":34.4101404,"lng":108.788946,"segIdx":13,"order":2},{"lat":34.4127402,"lng":108.7932957,"segIdx":13,"order":3},{"lat":34.4144408,"lng":108.7948844,"segIdx":13,"order":4},{"lat":34.4164108,"lng":108.795535,"segIdx":13,"order":5},{"lat":34.4199558,"lng":108.7951597,"segIdx":13,"order":6},{"lat":34.4213084,"lng":108.7950012,"segIdx":14,"order":0},{"lat":34.4299404,"lng":108.7939638,"segIdx":14,"order":1},{"lat":34.4315515,"lng":108.7937682,"segIdx":15,"order":0},{"lat":34.4422119,"lng":108.7917387,"segIdx":15,"order":1},{"lat":34.4544123,"lng":108.78137,"segIdx":15,"order":2},{"lat":34.4565875,"lng":108.7790837,"segIdx":16,"order":0},{"lat":34.4585482,"lng":108.7763381,"segIdx":16,"order":1},{"lat":34.4589159,"lng":108.7718075,"segIdx":16,"order":2},{"lat":34.4515572,"lng":108.7609319,"segIdx":16,"order":3},{"lat":34.4487859,"lng":108.759709,"segIdx":16,"order":4},{"lat":34.4435926,"lng":108.7605728,"segIdx":16,"order":5},{"lat":34.441199,"lng":108.7584218,"segIdx":16,"order":6}]},{"relationId":20015195,"key":"西安地铁|15","name":"西安地铁15号线：细柳→东兆余","ref":"15","network":"西安地铁","route":"subway","color":"#e06287","isLoop":false,"loopMode":"","loopReason":"","loopTerminalDistanceM":18773,"stations":[{"name":"细柳","lat":34.1613001,"lng":108.7876238,"rawLat":34.1613001,"rawLng":108.7876238,"transferKey":"细柳","platformKey":"20015195:0:细柳","osmRefs":["node/13383708297"]},{"name":"府君庙","lat":34.1612755,"lng":108.8002978,"rawLat":34.1612755,"rawLng":108.8002978,"transferKey":"府君庙","platformKey":"20015195:1:府君庙","osmRefs":["node/13383708296"]},{"name":"祝村西","lat":34.1613127,"lng":108.8138699,"rawLat":34.1613127,"rawLng":108.8138699,"transferKey":"祝村西","platformKey":"20015195:2:祝村西","osmRefs":["node/13383708295"]},{"name":"祝村","lat":34.1613478,"lng":108.8303728,"rawLat":34.1613478,"rawLng":108.8303728,"transferKey":"祝村","platformKey":"20015195:3:祝村","osmRefs":["node/13383708298"]},{"name":"郭杜西","lat":34.1615322,"lng":108.8412115,"rawLat":34.1615322,"rawLng":108.8412115,"transferKey":"郭杜西","platformKey":"20015195:4:郭杜西","osmRefs":["node/13383708299"]},{"name":"郭杜","lat":34.1611503,"lng":108.8591655,"rawLat":34.1611503,"rawLng":108.8591655,"transferKey":"郭杜","platformKey":"20015195:5:郭杜","osmRefs":["node/13383731663"]},{"name":"樱花广场","lat":34.1611955,"lng":108.8740088,"rawLat":34.1611955,"rawLng":108.8740088,"transferKey":"樱花广场","platformKey":"20015195:6:樱花广场","osmRefs":["node/13383731658"]},{"name":"邮电大学","lat":34.1593812,"lng":108.8987957,"rawLat":34.1593812,"rawLng":108.8987957,"transferKey":"邮电大学","platformKey":"20015195:7:邮电大学","osmRefs":["node/13383731657"]},{"name":"长安广场","lat":34.1584933,"lng":108.9241063,"rawLat":34.1584933,"rawLng":108.9241063,"transferKey":"长安广场","platformKey":"20015195:8:长安广场","osmRefs":["node/13383731656"]},{"name":"航天城","lat":34.1571613,"lng":108.9388791,"rawLat":34.1571613,"rawLng":108.9388791,"transferKey":"航天城","platformKey":"20015195:9:航天城","osmRefs":["node/13383731655"]},{"name":"皇子坡","lat":34.1559456,"lng":108.9568662,"rawLat":34.1559456,"rawLng":108.9568662,"transferKey":"皇子坡","platformKey":"20015195:10:皇子坡","osmRefs":["node/13383731654"]},{"name":"东长安街","lat":34.1557471,"lng":108.9708093,"rawLat":34.1557471,"rawLng":108.9708093,"transferKey":"东长安街","platformKey":"20015195:11:东长安街","osmRefs":["node/13383731653"]},{"name":"东兆余","lat":34.1567984,"lng":108.9915789,"rawLat":34.1567984,"rawLng":108.9915789,"transferKey":"东兆余","platformKey":"20015195:12:东兆余","osmRefs":["node/13383731652"]}],"waypoints":[{"lat":34.161298,"lng":108.7887199,"segIdx":0,"order":0},{"lat":34.1612775,"lng":108.7996141,"segIdx":0,"order":1},{"lat":34.1613051,"lng":108.8111143,"segIdx":1,"order":0},{"lat":34.1613609,"lng":108.8318245,"segIdx":3,"order":0},{"lat":34.1616481,"lng":108.8396963,"segIdx":3,"order":1},{"lat":34.1614612,"lng":108.8421765,"segIdx":4,"order":0},{"lat":34.1612454,"lng":108.8584186,"segIdx":4,"order":1},{"lat":34.1610407,"lng":108.8600266,"segIdx":5,"order":0},{"lat":34.1614367,"lng":108.8733673,"segIdx":5,"order":1},{"lat":34.1607798,"lng":108.8750939,"segIdx":6,"order":0},{"lat":34.1597463,"lng":108.8790233,"segIdx":6,"order":1},{"lat":34.1594045,"lng":108.8980318,"segIdx":6,"order":2},{"lat":34.1593363,"lng":108.9002652,"segIdx":7,"order":0},{"lat":34.1585516,"lng":108.922896,"segIdx":7,"order":1},{"lat":34.1584441,"lng":108.9251286,"segIdx":8,"order":0},{"lat":34.157172,"lng":108.9382611,"segIdx":8,"order":1},{"lat":34.1571378,"lng":108.9402431,"segIdx":9,"order":0},{"lat":34.1559469,"lng":108.9560891,"segIdx":9,"order":1},{"lat":34.1559436,"lng":108.9584526,"segIdx":10,"order":0},{"lat":34.1557237,"lng":108.9699563,"segIdx":10,"order":1},{"lat":34.1557814,"lng":108.9721102,"segIdx":11,"order":0},{"lat":34.1567393,"lng":108.9901166,"segIdx":11,"order":1}]},{"relationId":16104050,"key":"西安地铁|16","name":"西安地铁16号线：秦创原中心 → 诗经里","ref":"16","network":"西安地铁","route":"subway","color":"#ea8464","isLoop":false,"loopMode":"","loopReason":"","loopTerminalDistanceM":12741,"stations":[{"name":"秦创原中心","lat":34.3389229,"lng":108.7817279,"rawLat":34.3389229,"rawLng":108.7817279,"transferKey":"秦创原中心","platformKey":"16104050:0:秦创原中心","osmRefs":["node/11019586185"]},{"name":"西咸大厦","lat":34.3303805,"lng":108.7780125,"rawLat":34.3303805,"rawLng":108.7780125,"transferKey":"西咸大厦","platformKey":"16104050:1:西咸大厦","osmRefs":["node/11019667177"]},{"name":"上林路","lat":34.3139559,"lng":108.7724949,"rawLat":34.3139559,"rawLng":108.7724949,"transferKey":"上林路","platformKey":"16104050:2:上林路","osmRefs":["node/9560059896"]},{"name":"复兴大道北","lat":34.2981227,"lng":108.7653411,"rawLat":34.2981227,"rawLng":108.7653411,"transferKey":"复兴大道北","platformKey":"16104050:3:复兴大道北","osmRefs":["node/9247949031"]},{"name":"西安国际足球中心","lat":34.2812448,"lng":108.7657205,"rawLat":34.2812448,"rawLng":108.7657205,"transferKey":"西安国际足球中心","platformKey":"16104050:4:西安国际足球中心","osmRefs":["node/9247949028"]},{"name":"细柳营","lat":34.2697711,"lng":108.7653684,"rawLat":34.2697711,"rawLng":108.7653684,"transferKey":"细柳营","platformKey":"16104050:5:细柳营","osmRefs":["node/9247949025"]},{"name":"沣东城市广场","lat":34.2610155,"lng":108.7655071,"rawLat":34.2610155,"rawLng":108.7655071,"transferKey":"沣东城市广场","platformKey":"16104050:6:沣东城市广场","osmRefs":["node/9247949024"]},{"name":"欢乐谷","lat":34.2454099,"lng":108.7431742,"rawLat":34.2454099,"rawLng":108.7431742,"transferKey":"欢乐谷","platformKey":"16104050:7:欢乐谷","osmRefs":["node/9429856118"]},{"name":"诗经里","lat":34.2289726,"lng":108.7426987,"rawLat":34.2289726,"rawLng":108.7426987,"transferKey":"诗经里","platformKey":"16104050:8:诗经里","osmRefs":["node/11019635753"]}],"waypoints":[{"lat":34.3378189,"lng":108.7817232,"segIdx":0,"order":0},{"lat":34.3362355,"lng":108.7815667,"segIdx":0,"order":1},{"lat":34.33268,"lng":108.7785682,"segIdx":0,"order":2},{"lat":34.3308826,"lng":108.7780172,"segIdx":0,"order":3},{"lat":34.3285256,"lng":108.7779949,"segIdx":1,"order":0},{"lat":34.325391,"lng":108.7775368,"segIdx":1,"order":1},{"lat":34.3190532,"lng":108.7744301,"segIdx":1,"order":2},{"lat":34.3122361,"lng":108.7716798,"segIdx":2,"order":0},{"lat":34.2996982,"lng":108.7654367,"segIdx":2,"order":1},{"lat":34.2966543,"lng":108.7653887,"segIdx":3,"order":0},{"lat":34.2822447,"lng":108.7657074,"segIdx":3,"order":1},{"lat":34.2802721,"lng":108.7657336,"segIdx":4,"order":0},{"lat":34.2715137,"lng":108.7653295,"segIdx":4,"order":1},{"lat":34.2514898,"lng":108.7655155,"segIdx":6,"order":0},{"lat":34.2505426,"lng":108.7651133,"segIdx":6,"order":1},{"lat":34.2500348,"lng":108.7637083,"segIdx":6,"order":2},{"lat":34.2500986,"lng":108.7444272,"segIdx":6,"order":3},{"lat":34.2471703,"lng":108.7431806,"segIdx":6,"order":4},{"lat":34.230462,"lng":108.7427056,"segIdx":7,"order":0}]},{"relationId":17925372,"key":"西安云巴|云巴","name":"西安高新云巴线：鱼化寨→恒业大道","ref":"云巴","network":"西安云巴","route":"light_rail","color":"#00a5ff","isLoop":false,"loopMode":"","loopReason":"","loopTerminalDistanceM":9178,"stations":[{"name":"鱼化寨","lat":34.2391399,"lng":108.8415622,"rawLat":34.2391399,"rawLng":108.8415622,"transferKey":"鱼化寨","platformKey":"17925372:0:鱼化寨","osmRefs":["node/11869805794"]},{"name":"西晁","lat":34.2378398,"lng":108.8331322,"rawLat":34.2378398,"rawLng":108.8331322,"transferKey":"西晁","platformKey":"17925372:1:西晁","osmRefs":["node/11869805793"]},{"name":"天谷四路","lat":34.2248107,"lng":108.8314009,"rawLat":34.2248107,"rawLng":108.8314009,"transferKey":"天谷四路","platformKey":"17925372:2:天谷四路","osmRefs":["node/11869805791"]},{"name":"省图高新馆","lat":34.2142522,"lng":108.8320294,"rawLat":34.2142522,"rawLng":108.8320294,"transferKey":"省图高新馆","platformKey":"17925372:3:省图高新馆","osmRefs":["node/11869805789"]},{"name":"软件新城","lat":34.2064956,"lng":108.8318682,"rawLat":34.2064956,"rawLng":108.8318682,"transferKey":"软件新城","platformKey":"17925372:4:软件新城","osmRefs":["node/11869805787"]},{"name":"锦业路西","lat":34.1975814,"lng":108.8317049,"rawLat":34.1975814,"rawLng":108.8317049,"transferKey":"锦业路西","platformKey":"17925372:5:锦业路西","osmRefs":["node/11869805785"]},{"name":"丈八七路","lat":34.1953929,"lng":108.8363844,"rawLat":34.1953929,"rawLng":108.8363844,"transferKey":"丈八七路","platformKey":"17925372:6:丈八七路","osmRefs":["node/11869805782"]},{"name":"东滩","lat":34.1999636,"lng":108.8454964,"rawLat":34.1999636,"rawLng":108.8454964,"transferKey":"东滩","platformKey":"17925372:7:东滩","osmRefs":["node/11869805781"]},{"name":"丈八五路","lat":34.1999546,"lng":108.8580792,"rawLat":34.1999546,"rawLng":108.8580792,"transferKey":"丈八五路","platformKey":"17925372:8:丈八五路","osmRefs":["node/11869805779"]},{"name":"丈八四路","lat":34.1947739,"lng":108.8646526,"rawLat":34.1947739,"rawLng":108.8646526,"transferKey":"丈八四路","platformKey":"17925372:9:丈八四路","osmRefs":["node/11869805777"]},{"name":"付村","lat":34.1833789,"lng":108.8645529,"rawLat":34.1833789,"rawLng":108.8645529,"transferKey":"付村","platformKey":"17925372:10:付村","osmRefs":["node/11869805775"]},{"name":"紫薇田园都市","lat":34.1744561,"lng":108.8645422,"rawLat":34.1744561,"rawLng":108.8645422,"transferKey":"紫薇田园都市","platformKey":"17925372:11:紫薇田园都市","osmRefs":["node/11869805772"]},{"name":"时代广场","lat":34.1681917,"lng":108.8622387,"rawLat":34.1681917,"rawLng":108.8622387,"transferKey":"时代广场","platformKey":"17925372:12:时代广场","osmRefs":["node/11869805771"]},{"name":"发展大道","lat":34.168179,"lng":108.8522003,"rawLat":34.168179,"rawLng":108.8522003,"transferKey":"发展大道","platformKey":"17925372:13:发展大道","osmRefs":["node/11869770964"]},{"name":"西太路","lat":34.1681747,"lng":108.8427849,"rawLat":34.1681747,"rawLng":108.8427849,"transferKey":"西太路","platformKey":"17925372:14:西太路","osmRefs":["node/11869770962"]},{"name":"毕原二路","lat":34.1684204,"lng":108.8304908,"rawLat":34.1684204,"rawLng":108.8304908,"transferKey":"毕原二路","platformKey":"17925372:15:毕原二路","osmRefs":["node/11869770960"]},{"name":"祝村","lat":34.1620375,"lng":108.8274666,"rawLat":34.1620375,"rawLng":108.8274666,"transferKey":"祝村","platformKey":"17925372:16:祝村","osmRefs":["node/11869770943"]},{"name":"恒业大道","lat":34.1576622,"lng":108.8255866,"rawLat":34.1576622,"rawLng":108.8255866,"transferKey":"恒业大道","platformKey":"17925372:17:恒业大道","osmRefs":["node/11869770941"]}],"waypoints":[{"lat":34.2391361,"lng":108.8384954,"segIdx":0,"order":0},{"lat":34.2391043,"lng":108.8342413,"segIdx":0,"order":1},{"lat":34.2384674,"lng":108.8332833,"segIdx":0,"order":2},{"lat":34.2364333,"lng":108.8329432,"segIdx":1,"order":0},{"lat":34.2253295,"lng":108.8314707,"segIdx":1,"order":1},{"lat":34.2241712,"lng":108.8313427,"segIdx":2,"order":0},{"lat":34.2155235,"lng":108.83238,"segIdx":2,"order":1},{"lat":34.2136868,"lng":108.8318837,"segIdx":3,"order":0},{"lat":34.2071841,"lng":108.8318389,"segIdx":3,"order":1},{"lat":34.2031345,"lng":108.8318562,"segIdx":4,"order":0},{"lat":34.201855,"lng":108.8317446,"segIdx":4,"order":1},{"lat":34.1968934,"lng":108.8317249,"segIdx":5,"order":0},{"lat":34.1956037,"lng":108.8327243,"segIdx":5,"order":1},{"lat":34.1954077,"lng":108.8352284,"segIdx":5,"order":2},{"lat":34.1954336,"lng":108.838257,"segIdx":6,"order":0},{"lat":34.1959423,"lng":108.8413532,"segIdx":6,"order":1},{"lat":34.1997682,"lng":108.8418374,"segIdx":6,"order":2},{"lat":34.1999999,"lng":108.8448429,"segIdx":6,"order":3},{"lat":34.1999799,"lng":108.8462987,"segIdx":7,"order":0},{"lat":34.199985,"lng":108.8555216,"segIdx":7,"order":1},{"lat":34.1999864,"lng":108.8605465,"segIdx":8,"order":0},{"lat":34.1997742,"lng":108.8644826,"segIdx":8,"order":1},{"lat":34.1957078,"lng":108.8646655,"segIdx":8,"order":2},{"lat":34.1938792,"lng":108.8646349,"segIdx":9,"order":0},{"lat":34.184447,"lng":108.8645554,"segIdx":9,"order":1},{"lat":34.182612,"lng":108.8645667,"segIdx":10,"order":0},{"lat":34.1754866,"lng":108.8645516,"segIdx":10,"order":1},{"lat":34.1738809,"lng":108.864537,"segIdx":11,"order":0},{"lat":34.1695616,"lng":108.8644762,"segIdx":11,"order":1},{"lat":34.1683891,"lng":108.8633045,"segIdx":11,"order":2},{"lat":34.1681824,"lng":108.8597986,"segIdx":12,"order":0},{"lat":34.1681803,"lng":108.8529772,"segIdx":12,"order":1},{"lat":34.1681585,"lng":108.8501619,"segIdx":13,"order":0},{"lat":34.1681514,"lng":108.843634,"segIdx":13,"order":1},{"lat":34.1682543,"lng":108.8417882,"segIdx":14,"order":0},{"lat":34.1684326,"lng":108.8357022,"segIdx":14,"order":1},{"lat":34.1684229,"lng":108.8297664,"segIdx":15,"order":0},{"lat":34.16738,"lng":108.8277977,"segIdx":15,"order":1},{"lat":34.1625833,"lng":108.8274722,"segIdx":15,"order":2},{"lat":34.1613018,"lng":108.8274522,"segIdx":16,"order":0},{"lat":34.1587213,"lng":108.8262521,"segIdx":16,"order":1}]}],"summary":{"routes":13,"stations":303,"waypoints":725,"relationsRead":14,"relationsMatched":14,"relationsFetched":14,"failedRelations":[],"snapshot":true,"generatedAt":"2026-07-15T15:07:53.569Z","deduplicated":true,"operatingOnly":true}}